Workbook
Name Comprar: [1]Param!#REF!
Name início_da_tarefa: [2]CronogramaDeProjeto!$E1
Name Início_do_projeto: '[3]Gráfico de Gantt'!$G$5
Name Início_do_projeto: '[3]Gráfico de Gantt'!$G$5
Name Início_do_projeto: '[4]Gráfico de Gantt'!$G$5
Name Início_do_projeto: '[4]Gráfico de Gantt'!$G$5
Name Início_do_projeto: '[3]Gráfico de Gantt'!$G$5
Name Início_do_projeto: '[4]Gráfico de Gantt'!$G$5
Name Início_do_projeto: '[3]Gráfico de Gantt'!$G$5
Name Início_do_projeto: '[4]Gráfico de Gantt'!$G$5
Name Início_do_projeto: '[5]Gráfico de Gantt'!$G$5
Name Início_do_projeto: '[3]Gráfico de Gantt'!$G$5
Name Início_do_projeto: 'Gráfico de Gantt'!$G$5
Name Periodicidade: [6]Param!$AB$5:$AB$9
Name progresso_da_tarefa: [2]CronogramaDeProjeto!$D1
Name Semana_de_exibição: '[3]Gráfico de Gantt'!$G$6
Name Semana_de_exibição: '[3]Gráfico de Gantt'!$G$6
Name Semana_de_exibição: '[4]Gráfico de Gantt'!$G$6
Name Semana_de_exibição: '[4]Gráfico de Gantt'!$G$6
Name Semana_de_exibição: '[3]Gráfico de Gantt'!$G$6
Name Semana_de_exibição: '[4]Gráfico de Gantt'!$G$6
Name Semana_de_exibição: '[3]Gráfico de Gantt'!$G$6
Name Semana_de_exibição: '[4]Gráfico de Gantt'!$G$6
Name Semana_de_exibição: '[5]Gráfico de Gantt'!$G$6
Name Semana_de_exibição: '[3]Gráfico de Gantt'!$G$6
Name Semana_de_exibição: 'Gráfico de Gantt'!$G$6
Name Status: [1]Param!#REF!
Name término_da_tarefa: [2]CronogramaDeProjeto!$F1
Name VersaoExcel: [6]Param!$D$15:$E$15
Name VersaoSR: [6]Param!$C$24:$C$26

Sheet Project Charter

Sheet WBS-MACRO-ATIVIDADE

Sheet WBS_Detalhado (ordem etapas)
B7: 4.1 Plano de ação detalhado da WBS (com dependência, tempo e recurso) | P7: FAREMOS MAIS PARA FRENTE
B9: Ref | C9: Etapas – Atividades - | D9: Dependência | E9: Data Início | F9: Data Fim | G9: Duração em semanas | H9: Conclusão | I9: Responsável | J9: Recursos | K9: Custos | L9: Obs | O9: Rede de Precedência de Atividades
B10: 1 | C10: Iniciação | D10: — | E10: 45873 | F10: 45880 | P10: Atividades | Q10: Dependência | R10: Duração em semanas
B11: 1.1 | C11: Entendimento das necessidades do cliente | D11: 1 | E11: 45873 | F11: 45874 | G11: 1 | H11: 1ª | I11: GERENTE DE PROJETO | J11: Pessoas | K11: 200 | O11: 1 | P11: Iniciação | Q11: NÃO | R11: 6
B12: 1.2 | C12: Formação da equipe de design e desenvolvimento | D12: 1.1 | E12: 45875 | F12: 45876 | G12: 1 | H12: 1ª | I12: GERENTE DE PROJETO | J12: Pessoas | K12: 150 | O12: 2 | P12: Planejamento | Q12: Iniciação | R12: 11
B13: 1.3 | C13: Identificação de funcionalidades e recursos | D13: 1.2 | E13: 45877 | F13: 45880 | G13: 1 | H13: 1ª | I13: GERENTE DE PROJETO | J13: Pessoas | K13: 220 | O13: 3 | P13: Design e Prototipagem | Q13: Iniciação | R13: 8
B14: 2 | C14: Planejamento | D14: 1.3 | E14: 45881 | F14: 45891 | G14: 1 | H14: 2ª | K14: =SUM(K11:K13) -> 570 | O14: 4 | P14: Desenvolvimento | Q14: Planejamento/Design e Prototipagem | R14: 11
B15: 2.1 | C15: Análise de mercado (foodtechs e concorrentes) | D15: 1.3 | E15: 45881 | F15: 45882 | G15: 2 | H15: 2ª | I15: GERENTE DE PROJETO | J15: Pessoas | K15: 180 | O15: 5 | P15: Integração com sistemas de monitoramento de saúde | Q15: Desenvolvimento | R15: 5
B16: 2.2 | C16: Definir os requisitos detalhados do sistema | D16: 2.1 | E16: 45883 | F16: 45890 | G16: 1 | H16: 2ª | I16: GERENTE DE PROJETO | J16: Pessoas | K16: 250 | O16: 6 | P16: Testes | Q16: Integração com sistemas de monitoramento de saúde | R16: 3
B17: 2.2.1 | C17: Definição de stakeholders | D17: 2.2 | E17: 45883 | F17: 45884 | G17: 2 | H17: 2ª | I17: GERENTE DE PROJETO | J17: Pessoas | K17: 150 | O17: 7 | P17: Lançamento (Stakeholders internos) | Q17: Testes | R17: 6
B18: 2.2.2 | C18: Planos de pesquisa de público-alvo | D18: 2.2.1 | E18: 45887 | F18: 45888 | G18: 1 | H18: 1ª | I18: GERENTE DE PROJETO | J18: Pessoas | K18: 150 | O18: 8 | P18: Pós-lançamento (Stakeholders internos) | Q18: Lançamento (Stakeholders internos) | R18: 6
B19: 2.2.3 | C19: Pesquisa por ferramentas | D19: 2.2.2 | E19: 45889 | F19: 45889 | G19: 1 | H19: 1ª | I19: GERENTE DE PROJETO | J19: Pessoas | K19: 120 | O19: 9 | P19: Marketing e Divulgação para o Mercado | Q19: Pós-lançamento (Stakeholders internos) | R19: 6
B20: 2.2.4 | C20: Integração com sistemas de banco de dados | D20: 2.2.3 | E20: 45890 | F20: 45890 | G20: 1 | H20: 1ª | I20: GERENTE DE PROJETO | J20: Pessoas | K20: 130 | O20: 10 | P20: Avaliação e Aperfeiçoamento | Q20: Marketing e Divulgação | R20: 6
B21: 2.2.5 | C21: Criação de cronograma e metas | D21: 2.2.4 | E21: 45891 | F21: 45891 | G21: 1 | H21: 1ª | I21: GERENTE DE PROJETO | J21: Pessoas | K21: 120 | O21: 11 | P21: Expansão | Q21: Avaliação e Aperfeiçoamento | R21: 6
B22: 3 | C22: Design e Prototipagem | D22: 2.2.5 | E22: 45894 | F22: 45905 | G22: 1 | H22: 1ª | K22: =SUM(K15:K21) -> 1100
B23: 3.1 | C23: Design UI | D23: 2.2.5 | E23: 45894 | F23: 45895 | G23: 2 | H23: 2ª | I23: DESIGN | J23: Pessoas | K23: 220
B24: 3.2 | C24: Design UX | D24: 3.1 | E24: 45896 | F24: 45897 | G24: 1 | H24: 1ª | I24: DESIGN | J24: Pessoas | K24: 220
B25: 3.3 | C25: Navegação e funcionalidades | D25: 3.2 | E25: 45898 | F25: 45898 | G25: 1 | H25: 1ª | I25: DESIGN | J25: Pessoas | K25: 180
B26: 3.4 | C26: Protótipos interativos | D26: 3.3 | E26: 45901 | F26: 45902 | G26: 1 | H26: 1ª | I26: DESIGN | J26: Pessoas | K26: 220
B27: 3.5 | C27: Interface limpa e intuitiva | D27: 3.4 | E27: 45903 | F27: 45903 | G27: 1 | H27: 1ª | I27: DESIGN | J27: Pessoas | K27: 180
B28: 3.6 | C28: Teste de UI / UX | D28: 3.5 | E28: 45904 | F28: 45905 | G28: 1 | H28: 1ª | I28: DESIGN | J28: Pessoas | K28: 220
B29: 4 | C29: Desenvolvimento | D29: 3.6 | E29: 45908 | F29: 45926 | G29: 1 | H29: 1ª | K29: =SUM(K23:K28) -> 1240
B30: 4.1 | C30: Definir a estrutura do sistema | D30: 3.6 | E30: 45908 | F30: 45910 | G30: 3 | H30: 3ª | I30: DESENVOLVIMENTO | J30: Pessoas | K30: 250
B31: 4.2 | C31: Desenvolver módulos principais | D31: 4.1 | E31: 45911 | F31: 45926 | G31: 2 | H31: 2ª | I31: DESENVOLVIMENTO | J31: Pessoas | K31: 260
B32: 4.2.1 | C32: Código front-end | D32: 4.2 | E32: 45911 | F32: 45915 | G32: 3 | H32: 3ª | I32: DESENVOLVIMENTO | J32: Pessoas | K32: 300
B33: 4.2.2 | C33: Código back-end | D33: 4.2.1 | E33: 45916 | F33: 45918 | G33: 2 | H33: 1ª | I33: DESENVOLVIMENTO | J33: Pessoas | K33: 260
B34: 4.2.3 | C34: Gerador de planos de adaptação | D34: 4.2.2 | E34: 45919 | F34: 45923 | G34: 2 | H34: 2ª | I34: DESENVOLVIMENTO | J34: Pessoas | K34: 240
B35: 4.2.4 | C35: Módulo de identificação e captação de cliente | D35: 4.2.3 | E35: 45924 | F35: 45926 | G35: 2 | H35: 2ª | I35: DESENVOLVIMENTO | J35: Pessoas | K35: 240
B36: 5 | C36: Integração com APIs | D36: 4.2.4 | E36: 45929 | F36: 45936 | G36: 1 | H36: 1ª | I36: DESENVOLVIMENTO | J36: Pessoas | K36: 240
B37: 5.1 | C37: Integração com sistemas de monitoramento de saúde | D37: 5 | E37: 45929 | F37: 45930 | G37: 2 | H37: 2ª | K37: =SUM(K23:K28) -> 1240
B38: 5.2 | C38: Integração com diversos sistemas | D38: 5.1 | E38: 45931 | F38: 45932 | G38: 1 | H38: 2ª | I38: SEGURANÇA | J38: Pessoas | K38: 180
B39: 5.3 | C39: Garantia de segurança e privacidade | D39: 5.2 | E39: 45933 | F39: 45936 | G39: 1 | H39: 2ª | I39: SEGURANÇA | J39: Pessoas | K39: 200
B40: 6 | C40: Integração e sincronização de dados | D40: 5.3 | E40: 45937 | F40: 45943 | G40: 1 | H40: 2ª | I40: SEGURANÇA | J40: Pessoas | K40: 500
B41: 6.1 | C41: Testes | D41: 5.3 | E41: 45937 | F41: 45938 | G41: 1 | H41: 1ª | K41: =SUM(K38:K40) -> 880
B42: 6.1.2 | C42: Testes de qualidade e desempenho | D42: 6.1 | E42: 45939 | F42: 45939 | G42: 1 | H42: 1ª | I42: QUALIDADE | J42: Pessoas | K42: 200
B43: 6.1.3 | C43: Testes de usabilidade | D43: 6.1.2 | E43: 45940 | F43: 45943 | G43: 1 | H43: 1ª | I43: QUALIDADE | J43: Pessoas | K43: 260
B44: 7 | C44: Identificação e correção de bugs | D44: 6.1.3 | E44: 45944 | F44: 45950 | G44: 1 | H44: 1ª | I44: QUALIDADE | J44: Pessoas | K44: 400
B45: 7.1.1 | C45: Lançamento (Stakeholders internos) | D45: 6.1.3 | E45: 45944 | F45: 45945 | G45: 1 | H45: 1ª | K45: =SUM(K42:K44) -> 860
B46: 7.1.2 | C46: Criar material de marketing para o cliente | D46: 7.1.1 | E46: 45946 | F46: 45946 | G46: 1 | H46: 2ª | I46: REDES | J46: Pessoas | K46: 200
B47: 7.1.3 | C47: Criar materiais de marketing | D47: 7.1.2 | E47: 45947 | F47: 45950 | G47: 1 | H47: 2ª | I47: COMERCIAL | J47: Pessoas | K47: 240
A48: . | B48: 8 | C48: Preparar infraestrutura no marketplace | D48: 7.1.3 | E48: 45951 | F48: 45957 | G48: 1 | H48: 2ª | I48: COMERCIAL | J48: Pessoas | K48: 400
B49: 8.1.1 | C49: Pós-lançamento (Stakeholders internos) | D49: 7.1.3 | E49: 45951 | F49: 45952 | G49: 1 | H49: 1ª | K49: =SUM(K46:K48) -> 840
B50: 8.1.2 | C50: Monitoramento de métricas e feedback | D50: 8.1.1 | E50: 45953 | F50: 45953 | G50: 1 | H50: 2ª | I50: EQUIPE TÉCNICA | J50: Pessoas | K50: 180
B51: 8.1.3 | C51: Realização de atualizações e melhorias contínuas | D51: 8.1.2 | E51: 45954 | F51: 45957 | G51: 1 | H51: 2ª | I51: EQUIPE TÉCNICA | J51: Pessoas | K51: 220
B52: 9 | C52: Suporte e solução de dúvidas | D52: 8.1.3 | E52: 45958 | F52: 45966 | G52: 1 | H52: 2ª | I52: EQUIPE TÉCNICA | J52: Pessoas | K52: 200
B53: 9.1.1 | C53: Marketing e Divulgação - para o Mercado | D53: 8.1.3 | E53: 45958 | F53: 45959 | G53: 1 | H53: 1ª | K53: =SUM(K50:K52) -> 600
B54: 9.1.2 | C54: Estratégias de marketing | D54: 9.1.1 | E54: 45960 | F54: 45964 | G54: 1 | H54: 2ª | I54: EQUIPE TÉCNICA | J54: Pessoas | K54: 220
B55: 9.1.3 | C55: Colaboração com sistemas de reviews | D55: 9.1.2 | E55: 45965 | F55: 45966 | G55: 1 | H55: 2ª | I55: EQUIPE TÉCNICA | J55: Pessoas | K55: 240
B56: 10 | C56: Campanhas em mídias sociais e anúncios online | D56: 9.1.3 | E56: 45967 | F56: 45974 | G56: 1 | H56: 2ª | I56: EQUIPE TÉCNICA | J56: Pessoas | K56: 1500
B57: 10.1.1 | C57: Avaliação e Aperfeiçoamento | D57: 9.1.3 | E57: 45967 | F57: 45969 | G57: 1 | H57: 1ª | K57: =SUM(K54:K56) -> 1960
B58: 10.1.2 | C58: Análise de desempenho | D58: 10.1.1 | E58: 45971 | F58: 45972 | G58: 1 | H58: 2ª | I58: DESEMPENHO | J58: Pessoas | K58: 200
B59: 10.1.3 | C59: Coletar feedback e implementar melhorias | D59: 10.1.2 | E59: 45973 | F59: 45974 | G59: 1 | H59: 2ª | I59: COMERCIAL | J59: Pessoas | K59: 200
B60: 11 | C60: Adaptação ao mercado | D60: 10.1.3 | E60: 45975 | F60: 45986 | G60: 1 | H60: 2ª | I60: COMERCIAL | J60: Pessoas | K60: 500
B61: 11.1.1 | C61: Expansão | D61: 10.1.3 | E61: 45975 | F61: 45978 | G61: 2 | H61: 2ª | K61: =SUM(K58:K60) -> 900
B62: 11.1.2 | C62: Análise de expansão de mercado | D62: 11.1.1 | E62: 45979 | F62: 45981 | G62: 1 | H62: 2ª | I62: EQUIPE TÉCNICA | J62: Pessoas | K62: 220
B63: 11.1.3 | C63: Aprimoramento dos requisitos funcionais | D63: 11.1.2 | E63: 45982 | F63: 45986 | G63: 1 | H63: 2ª | I63: EQUIPE TÉCNICA | J63: Pessoas | K63: 260
B64: 11.1.3 | C64: Desenvolvimento de versão mobile | D64: 11.1.2 | E64: 45982 | F64: 45986 | G64: 1 | H64: 2ª | I64: EQUIPE TÉCNICA | J64: Pessoas | K64: 4000
D65: 11.1.3 | E65: 45982 | F65: 45986 | K65: =SUM(K62:K64) -> 4480
D66: TOTAL | K66: =SUM(K14,K22,K29,K37,K41,K45,K53,K49,K61,K65,K22,K29,K37,K41,K45,K53) -> 18630

Sheet WBS_Detalhado (ordem depend)
B6: 4.2 Plano de ação detalhado da WBS (com dependência, tempo e recurso)
B8: Ref | C8: Etapas – Atividades - | D8: Dependência | E8: Duração em semanas | F8: Conclusão | G8: Responsável | H8: Recursos | I8: Obs
B9: 1.1 | C9: Entendimento das necessidades do cliente | D9: 1 | E9: 1 | F9: 1ª | G9: GERENTE DE PROJETO | H9: Pessoas | I9: -
B10: 1.2 | C10: Formação da equipe de design e desenvolvimento | D10: 1.1 | E10: 1 | F10: 2ª | G10: GERENTE DE PROJETO | H10: Pessoas | I10: -
B11: 1.3 | C11: Identificação de funcionalidades e recursos | D11: 1.2 | E11: 1 | F11: 2ª | G11: GERENTE DE PROJETO | H11: Pessoas
B12: 2.1 | C12: Análise de mercado (concorrentes e tendências foodtech) | D12: 1.3 | E12: 2 | F12: 2ª | G12: GERENTE DE PROJETO | H12: Pessoas
B13: 2.2 | C13: Definição dos requisitos detalhados do sistema | D13: 2.1 | E13: 1 | F13: 2ª | G13: GERENTE DE PROJETO | H13: Pessoas
B14: 2.2.1 | C14: Identificação dos stakeholders | D14: 2.2 | E14: 2 | F14: 2ª | G14: GERENTE DE PROJETO | H14: Pessoas | I14: -
B15: 2.2.2 | C15: Pesquisa de público-alvo | D15: 2.2.1 | E15: 1 | F15: 2ª | G15: GERENTE DE PROJETO | H15: Pessoas | I15: -
B16: 2.2.3 | C16: Levantamento de ferramentas tecnológicas | D16: 2.2.2 | E16: 1 | F16: 1ª | G16: GERENTE DE PROJETO | H16: Pessoas | I16: -
B17: 2.2.4 | C17: Planejamento de integração com banco de dados | D17: 2.2.3 | E17: 1 | F17: 1ª | G17: GERENTE DE PROJETO | H17: Pessoas | I17: -
B18: 2.2.5 | C18: Definição do cronograma e metas | D18: 2.2.4 | E18: 1 | F18: 2ª | G18: GERENTE DE PROJETO | H18: Pessoas | I18: -
B19: 3.1 | C19: Design da interface (UI) | D19: 2.2.5 | E19: 2 | F19: 1ª | G19: DESIGN | H19: Pessoas | I19: -
B20: 3.2 | C20: Estrutura de experiência do usuário (UX) | D20: 3.1 | E20: 1 | F20: 1ª | G20: DESIGN | H20: Pessoas | I20: -
B21: 3.3 | C21: Definição da navegação e funcionalidades | D21: 3.2 | E21: 1 | F21: 1ª | G21: DESIGN | H21: Pessoas | I21: -
B22: 3.4 | C22: Criação de protótipos interativos | D22: 3.3 | E22: 1 | F22: 1ª | G22: DESIGN | H22: Pessoas | I22: -
B23: 3.5 | C23: Ajuste para interface limpa e intuitiva | D23: 3.4 | E23: 1 | F23: 1ª | G23: DESIGN | H23: Pessoas | I23: -
B24: 3.6 | C24: Testes de usabilidade da UI/UX | D24: 3.5 | E24: 1 | F24: 2ª | G24: DESIGN | H24: Pessoas | I24: -
B25: 4.1 | C25: Definição da arquitetura do sistema | D25: 3.6 | E25: 3 | F25: 2ª | G25: DESENVOLVIMENTO | H25: Pessoas | I25: -
... B30: 4.2.4 | C30: Implementação do módulo de identificação e captação de clientes | D30: 4.2.3 | E30: 2 | F30: 2ª | G30: DESENVOLVIMENTO | H30: Pessoas | I30: -
B31: 5 | C31: Integração com APIs externas | D31: 4.2.4 | E31: 1 | F31: 1ª | G31: DESENVOLVIMENTO | H31: Pessoas | I31: -
B32: 5.2 | C32: Integração com sistemas internos/externos | D32: 5.1 | E32: 1 | F32: 2ª | G32: SEGURANÇA | H32: Pessoas | I32: -
B33: 5.3 | C33: Garantia de segurança e privacidade dos dados | D33: 5.2 | E33: 1 | F33: 2ª | G33: SEGURANÇA | H33: Pessoas | I33: -
B34: 6 | C34: Sincronização de dados em tempo real | D34: 5.3 | E34: 1 | F34: 2ª | G34: SEGURANÇA | H34: Pessoas | I34: -
B35: 6.1.2 | C35: Testes de qualidade e desempenho | D35: 6.1 | E35: 1 | F35: 1ª | G35: QUALIDADE | H35: Pessoas | I35: -
B36: 6.1.3 | C36: Testes de usabilidade | D36: 6.1.2 | E36: 1 | F36: 1ª | G36: QUALIDADE | H36: Pessoas | I36: -
B37: 7 | C37: Identificar e corrigir bugs e problemas de interface | D37: 6.1.3 | E37: 1 | F37: 1ª | G37: QUALIDADE | H37: Pessoas | I37: -
B38: 7.1.2 | C38: Identificação e correção de bugs | D38: 7.1.1 | E38: 1 | F38: 1ª | G38: REDES | H38: Pessoas | I38: -
B39: 7.1.3 | C39: Criação de material de marketing para clientes | D39: 7.1.2 | E39: 1 | F39: 2ª | G39: COMERCIAL | H39: Pessoas | I39: -
B40: 8 | C40: Produção de materiais promocionais internos/externos | D40: 7.1.3 | E40: 1 | F40: 2ª | G40: COMERCIAL | H40: Pessoas | I40: -
B41: 8.1.2 | C41: Preparação da infraestrutura de publicação | D41: 8.1.1 | E41: 1 | F41: 2ª | G41: EQUIPE TÉCNICA | H41: Pessoas | I41: -
B42: 8.1.3 | C42: Avaliação nas lojas/plataformas de aplicativos | D42: 8.1.2 | E42: 1 | F42: 2ª | G42: EQUIPE TÉCNICA | H42: Pessoas | I42: -
B43: 9 | C43: Monitoramento de métricas e coleta de feedback | D43: 8.1.3 | E43: 1 | F43: 2ª | G43: EQUIPE TÉCNICA | H43: Pessoas | I43: -
B44: 9.1.2 | C44: Atualizações e melhorias contínuas | D44: 9.1.1 | E44: 1 | F44: 2ª | G44: EQUIPE TÉCNICA | H44: Pessoas | I44: -
B45: 9.1.3 | C45: Suporte e resolução de dúvidas | D45: 9.1.2 | E45: 1 | F45: 2ª | G45: EQUIPE TÉCNICA | H45: Pessoas | I45: -
B46: 10 | C46: Definição de estratégias de marketing | D46: 9.1.3 | E46: 1 | F46: 2ª | G46: EQUIPE TÉCNICA | H46: Pessoas | I46: -
B47: 10.1.2 | C47: Parcerias e colaboração com sistemas de reviews | D47: 10.1.1 | E47: 1 | F47: 2ª | G47: DESEMPENHO | H47: Pessoas | I47: -
B48: 10.1.3 | C48: Campanhas em mídias sociais e anúncios online | D48: 10.1.2 | E48: 1 | F48: 2ª | G48: COMERCIAL | H48: Pessoas | I48: -
B49: 11 | C49: Análise de desempenho do dashboard | D49: 10.1.3 | E49: 1 | F49: 2ª | G49: COMERCIAL | H49: Pessoas | I49: -
B50: 11.1.2 | C50: Coleta de feedback e implementação de melhorias | D50: 11.1.1 | E50: 1 | F50: 2ª | G50: EQUIPE TÉCNICA | H50: Pessoas | I50: -
B51: 11.1.3 | C51: Adaptação a mudanças de mercado | D51: 11.1.2 | E51: 1 | F51: 2ª | G51: EQUIPE TÉCNICA | H51: Pessoas | I51: -
B52: 11.1.3 | C52: Desenvolvimento de versão mobile nativa | D52: 11.1.2 | E52: 1 | F52: 2ª | G52: EQUIPE TÉCNICA | H52: Pessoas | I52: -

Sheet WBS- PLANILHA
A1: Análise de Stakeholders
A2: Projeto | B2: InovaTech
A3: Gerente do Projeto | B3: Adeilson, Bruna, Enzo, Daniela e Rafaela
A8: Entregas do Projeto | B8: A definir | C8: Atulizado Em | D8: 45901
A10: SAM | I10: SRM
A11: Stakeholder | B11: Objetivos | C11: Metas | D11: Motivações e Interesses | E11: Poder e influência | F11: Importância e Impacto | G11: Papéis & Responsabilidades | H11: Sintonia "fina" | I11: Área de Interesse | J11: Nível de Detalhe | K11: Formato | L11: Frequência | M11: Mecanismo de Entrega
A12: Cliente (Usuários Finais) | B12: Fornecer dados que comprovem a eficiência da análise de dados da Cannoli | C12: Capitar dados dos clientes e fazer uma análise eficiente e detalhada. | D12: Ser eficiente na análise de dado e no retorno visual dos dados. | E12: Influenciam o sucesso do trabalho de divulgação da Cannoli por meio de dados e feedback. | F12: Essencial para a aceitação e popularidade do sistema. | G12: Usar o sistema, fornecer feedback para a Cannoli, compartilhar dados. | H12: Manter os clientes satisfeitos, garantir que o aplicativo atenda às suas necessidades. | I12: Análise de dados | J12: Relatórios concisos e informativos, que destaquem eficiência da Cannoli para os clientes dela | K12: Coletar dados e analisa-los através de sistema digital. | L12: Diariamente. Ou conforme desejo do cliente. | M12: Relatórios entregues por sistema digital.
A13: Product Owner | B13: Garantir que o dashboard atenda às necessidades de negócio e esteja alinhado à visão estratégica do produto Cannoli. | C13: Priorizar backlog, validar requisitos, acompanhar desenvolvimento e assegurar entrega de valor contínuo. | D13: Garantir sucesso do produto no mercado, maximizar o ROI e manter o alinhamento entre áreas técnicas e de negócio. | E13: Alto (define prioridades, backlog e critérios de aceitação). | F13: Essencial para direcionar o time de desenvolvimento e garantir entregas de valor. | G13: Gerenciar backlog, definir prioridades, validar entregas, atuar como elo entre stakeholders e time técnico. | H13: Manter comunicação constante com desenvolvedores, marketing e alta gestão para alinhar expectativas. | I13: Estratégia do produto, roadmap, backlog, KPIs estratégicos. | J13: Alto (detalhes técnicos e de negócio para validação de requisitos). | K13: Relatórios executivos do andamento do backlog e dashboards de progresso. | L13: Semanal (sprints, reviews) e mensal (alinhamento estratégico). | M13: Reuniões rReuniões de sprint review, relatórios digitais e dashboards compartilhados.emotas, relatórios enviados por e-mail.
A14: Desenvolvedores | B14: Entregar um dashboard funcional, seguro e responsivo, com dados consistentes e IA básica. | C14: Concluir o MVP dentro do prazo, garantir qualidade técnica e atender requisitos funcionais/não funcionais. | D14: Aprendizado prático, desenvolvimento de portfólio, sucesso do projeto. | E14: Alto (definem viabilidade técnica e velocidade de entrega). | F14: Muito alto (sem eles não há entrega). | G14: Programar backend/frontend, modelar dados, implementar KPIs/IA, testar e documentar. | H14: Necessário alinhamento constante com Time Comercial e Stakeholders. | I14: Tecnologia e inovação (dev, dados, IA, segurança). | J14: Alto (precisam de requisitos claros e detalhados). | K14: Reuniões técnicas, backlog/Trello/GitHub. | L14: Semanal (sprints) + checkpoints rápidos. | M14: Relatórios de progresso, commits no repositório, versões do sistema.
A15: Time Comercial | B15: Garantir que o dashboard atenda às necessidades dos restaurantes e admins da Cannoli. | C15: Validar KPIs estratégicos, apoiar na definição de métricas e simulações de campanhas. | D15: Sucesso do produto no mercado, aumento de engajamento/fidelização, clareza nos dados. | E15: Médio (influenciam requisitos de negócio, mas não a execução técnica). | F15: Alto (sem alinhamento, risco de desenvolver algo que não gera valor). | G15: Definir requisitos de negócio, validar KPIs, dar feedback contínuo, apresentar aos stakeholders externos. | H15: Precisa estar em contato constante com Desenvolvedores e Administradores Cannoli. | I15: Estratégia, vendas, métricas de engajamento e campanhas. | J15: Médio (querem visão consolidada, não detalhes técnicos). | K15: Relatórios executivos, apresentações visuais do dashboard. | L15: Quinzenal (validação de entregas) + sob demanda em fases críticas. | M15: Demonstrações do dashboard, relatórios resumidos, reuniões de validação.
A16: Marketing | B16: Garantir que o dashboard gere insights úteis para campanhas e estratégias de engajamento. | C16: Apoiar na definição de métricas de retenção, ticket médio, comportamento do cliente e resultados de campanhas. | D16: Aumentar engajamento dos clientes, melhorar ROI das campanhas, ampliar a base de restaurantes parceiros. | E16: Médio (influencia requisitos de relatórios e indicadores, mas depende da equipe técnica para execução) | F16: Alto (as campanhas são decisivas para o sucesso do produto no mercado). | G16: Definir KPIs de marketing, validar relatórios, sugerir novas métricas de análise. | H16: Precisa alinhar com Desenvolvedores e Comercial para que os relatórios reflitam necessidades reais. | I16: Engajamento, campanhas, retenção, funil de clientes. | J16: Médio (querem relatórios claros e acionáveis). | K16: Relatórios visuais, gráficos e dashboards de impacto. | L16: Quinzenal ou mensal (dependendo do ciclo de campanhas). | M16: Relatórios executivos, dashboards interativos, reuniões de alinhamento.
A17: UX (User Experience) | B17: Garantir que a interface do dashboard seja intuitiva, responsiva e agradável de usar. | C17: Validar protótipos, acompanhar usabilidade, propor melhorias na navegação e acessibilidade. | D17: Aumentar satisfação dos usuários, reduzir curva de aprendizado, facilitar adoção do sistema. | E17: Médio (definem padrões de experiência, mas dependem dos devs para aplicar). | F17: Mantêm clientes engajados e reduzem riscos de abandono da plataforma. | G17: Criar protótipos, validar fluxos de navegação, aplicar testes de usabilidade, recomendar ajustes. | H17: Alinhamento próximo com Desenvolvedores e Comercial para equilibrar experiência e requisitos de negócio. | I17: Design, usabilidade, acessibilidade, responsividade. | J17: Alto (precisam entender microinterações e feedbacks de interface). | K17: Wireframes, protótipos, relatórios de testes de usabilidade. | L17: Semanal (durante fases de design e testes). | M17: Protótipos em Figma, relatórios de testes, reuniões de feedback.
A18: Equipe de Suporte ao Cliente | B18: Resolver problemas técnicos reportados pelos usuários e garantir suporte eficiente. | C18: Resolução rápida de problemas e satisfação contínua dos administradores e restaurantes. | D18: Manter os clientes satisfeitos, reduzir falhas no uso do sistema e garantir continuidade operacional. | E18: Podem influenciar diretamente a satisfação e retenção dos usuários finais. | F18: Mantêm os clientes satisfeitos e engajados. | G18: Responder dúvidas, resolver problemas técnicos, registrar feedback e encaminhar melhorias. | H18: Fornecer suporte ágil e eficaz, garantindo confiança no uso do dashboard. | I18: Problemas recorrentes de acesso, falhas técnicas e relatórios de uso da plataforma. | J18: Médio (detalhes sobre falhas, prazos de resolução e satisfação). | K18: Relatórios de incidentes e feedback estruturado. | L18: Mensal ou conforme demanda dos usuários. | M18: Reuniões virtuais e relatórios digitais enviados por e-mail/sistema.
A19: Gerência Executiva/Alta Administração | B19: Alinhar o dashboard com a visão estratégica da empresa, garantindo retorno financeiro e sucesso no mercado. | C19: Crescimento da base de clientes, aumento do ROI e fortalecimento da marca Cannoli. | D19: Sucesso do produto, crescimento financeiro e posicionamento competitivo. | E19: Definem estratégias, disponibilizam recursos e estabelecem prioridades. | F19: Decidem o rumo do produto e o impacto no negócio. | G19: Definir metas estratégicas, validar indicadores-chave, alocar recursos e acompanhar resultados. | H19: Manter alinhamento entre o dashboard e os objetivos estratégicos da empresa. | I19: Indicadores financeiros, métricas de ROI, crescimento da base de restaurantes parceiros. | J19: Alto (relatórios executivos consolidados com indicadores estratégicos). | K19: Relatórios executivos, dashboards de impacto e apresentações em PPT. | L19: Mensal ou trimestral, dependendo do ciclo estratégico. | M19: Reuniões presenciais ou virtuais, com relatórios e dashboards digitais.

Sheet Segunda Entrega -->

Sheet REDE_PERT_CPM-
A1: Ref | B1: Atividade | C1: Dependência | D1: Duração | E1: ES | F1: EF | G1: LS | H1: LF | I1: Folga | J1: Caminho Crítico | K1: Pred1 | L1: Pred2 | M1: Pred3 | N1: Makespan(M2) | O1: MinES_sucessoras
A2: 1 | B2: 1A. Definição dos objetivos do Projeto | D2: 3 | E2: =MAX(IFERROR(VLOOKUP(K2,$A$2:$F$21,6,FALSE),0),IFERROR(VLOOKUP(L2,$A$2:$F$21,6,FALSE),0),IFERROR(VLOOKUP(M2,$A$2:$F$21,6,FALSE),0)) -> 0 | F2: =E2+D2 -> 3 | G2: =H2-D2 -> 0 | H2: =IF(O2=1E+99,$N$2,O2) -> 3 | I2: =G2-E2 -> 0 | J2: =IF(I2=0,"Sim","Não") -> Sim | N2: 3 | O2: =MIN(IF($K$2:$K$21=A2,$E$2:$E$21,1E+99),IF($L$2:$L$21=A2,$E$2:$E$21,1E+99),IF($M$2:$M$21=A2,$E$2:$E$21,1E+99)) -> 1e+99
A3: 2 | B3: 1B. Formação da equipe do projeto | D3: 2 | E3: =MAX(IFERROR(VLOOKUP(K3,$A$2:$F$21,6,FALSE),0),IFERROR(VLOOKUP(L3,$A$2:$F$21,6,FALSE),0),IFERROR(VLOOKUP(M3,$A$2:$F$21,6,FALSE),0)) -> 0 | F3: =E3+D3 -> 2 | G3: =H3-D3 -> 1 | H3: =IF(O3=1E+99,$N$2,O3) -> 3 | I3: =G3-E3 -> 1 | J3: =IF(I3=0,"Sim","Não") -> Não | O3: =MIN(IF($K$2:$K$21=A3,$E$2:$E$21,1E+99),IF($L$2:$L$21=A3,$E$2:$E$21,1E+99),IF($M$2:$M$21=A3,$E$2:$E$21,1E+99)) -> 1e+99
A4: 3 | B4: 1C. Identificação dos stakeholders | C4: 1 | D4: 3 | E4: =MAX(IFERROR(VLOOKUP(K4,$A$2:$F$21,6,FALSE),0),IFERROR(VLOOKUP(L4,$A$2:$F$21,6,FALSE),0),IFERROR(VLOOKUP(M4,$A$2:$F$21,6,FALSE),0)) -> 0 | F4: =E4+D4 -> 3 | G4: =H4-D4 -> 0 | H4: =IF(O4=1E+99,$N$2,O4) -> 3 | I4: =G4-E4 -> 0 | J4: =IF(I4=0,"Sim","Não") -> Sim | K4: 1 | O4: =MIN(IF($K$2:$K$21=A4,$E$2:$E$21,1E+99),IF($L$2:$L$21=A4,$E$2:$E$21,1E+99),IF($M$2:$M$21=A4,$E$2:$E$21,1E+99)) -> 1e+99
A5: 4 | B5: 1D. Reunião de Kick Off | C5: 3 | D5: 1 | E5: =MAX(IFERROR(VLOOKUP(K5,$A$2:$F$21,6,FALSE),0),IFERROR(VLOOKUP(L5,$A$2:$F$21,6,FALSE),0),IFERROR(VLOOKUP(M5,$A$2:$F$21,6,FALSE),0)) -> 0 | F5: =E5+D5 -> 1 | G5: =H5-D5 -> 2 | H5: =IF(O5=1E+99,$N$2,O5) -> 3 | I5: =G5-E5 -> 2 | J5: =IF(I5=0,"Sim","Não") -> Não | K5: 3 | O5: =MIN(IF($K$2:$K$21=A5,$E$2:$E$21,1E+99),IF($L$2:$L$21=A5,$E$2:$E$21,1E+99),IF($M$2:$M$21=A5,$E$2:$E$21,1E+99)) -> 1e+99
A6: 5 | B6: 2A. Levantamento de Requisitos | C6: 2,3 | D6: 3 | E6: =MAX(IFERROR(VLOOKUP(K6,$A$2:$F$21,6,FALSE),0),IFERROR(VLOOKUP(L6,$A$2:$F$21,6,FALSE),0),IFERROR(VLOOKUP(M6,$A$2:$F$21,6,FALSE),0)) -> 0 | F6: =E6+D6 -> 3 | G6: =H6-D6 -> 0 | H6: =IF(O6=1E+99,$N$2,O6) -> 3 | I6: =G6-E6 -> 0 | J6: =IF(I6=0,"Sim","Não") -> Sim | K6: 2 | L6: 3 | O6: =MIN(IF($K$2:$K$21=A6,$E$2:$E$21,1E+99),IF($L$2:$L$21=A6,$E$2:$E$21,1E+99),IF($M$2:$M$21=A6,$E$2:$E$21,1E+99)) -> 1e+99
A7: 6 | B7: 2B. Entrevistas com Cannoli e Restaurantes | C7: 4 | D7: 2 | E7: =MAX(IFERROR(VLOOKUP(K7,$A$2:$F$21,6,FALSE),0),IFERROR(VLOOKUP(L7,$A$2:$F$21,6,FALSE),0),IFERROR(VLOOKUP(M7,$A$2:$F$21,6,FALSE),0)) -> 0 | F7: =E7+D7 -> 2 | G7: =H7-D7 -> 1 | H7: =IF(O7=1E+99,$N$2,O7) -> 3 | I7: =G7-E7 -> 1 | J7: =IF(I7=0,"Sim","Não") -> Não | K7: 4 | O7: =MIN(IF($K$2:$K$21=A7,$E$2:$E$21,1E+99),IF($L$2:$L$21=A7,$E$2:$E$21,1E+99),IF($M$2:$M$21=A7,$E$2:$E$21,1E+99)) -> 1e+99
A8: 7 | B8: 2C. Documentação de Requisitos Funcionais | C8: 5,6 | D8: 3 | E8: =MAX(IFERROR(VLOOKUP(K8,$A$2:$F$21,6,FALSE),0),IFERROR(VLOOKUP(L8,$A$2:$F$21,6,FALSE),0),IFERROR(VLOOKUP(M8,$A$2:$F$21,6,FALSE),0)) -> 0 | F8: =E8+D8 -> 3 | G8: =H8-D8 -> 0 | H8: =IF(O8=1E+99,$N$2,O8) -> 3 | I8: =G8-E8 -> 0 | J8: =IF(I8=0,"Sim","Não") -> Sim | K8: 5 | L8: 6 | O8: =MIN(IF($K$2:$K$21=A8,$E$2:$E$21,1E+99),IF($L$2:$L$21=A8,$E$2:$E$21,1E+99),IF($M$2:$M$21=A8,$E$2:$E$21,1E+99)) -> 1e+99
A9: 8 | B9: 2D. Documentação de Requisitos Não Funcionais | C9: 4,6 | D9: 3 | E9: =MAX(IFERROR(VLOOKUP(K9,$A$2:$F$21,6,FALSE),0),IFERROR(VLOOKUP(L9,$A$2:$F$21,6,FALSE),0),IFERROR(VLOOKUP(M9,$A$2:$F$21,6,FALSE),0)) -> 0 | F9: =E9+D9 -> 3 | G9: =H9-D9 -> 0 | H9: =IF(O9=1E+99,$N$2,O9) -> 3 | I9: =G9-E9 -> 0 | J9: =IF(I9=0,"Sim","Não") -> Sim | K9: 4 | L9: 6 | O9: =MIN(IF($K$2:$K$21=A9,$E$2:$E$21,1E+99),IF($L$2:$L$21=A9,$E$2:$E$21,1E+99),IF($M$2:$M$21=A9,$E$2:$E$21,1E+99)) -> 1e+99
A10: 9 | B10: 3A. UX - Experiência do Usuário | C10: 7 | D10: 3 | E10: =MAX(IFERROR(VLOOKUP(K10,$A$2:$F$21,6,FALSE),0),IFERROR(VLOOKUP(L10,$A$2:$F$21,6,FALSE),0),IFERROR(VLOOKUP(M10,$A$2:$F$21,6,FALSE),0)) -> 0 | F10: =E10+D10 -> 3 | G10: =H10-D10 -> 0 | H10: =IF(O10=1E+99,$N$2,O10) -> 3 | I10: =G10-E10 -> 0 | J10: =IF(I10=0,"Sim","Não") -> Sim | K10: 7 | O10: =MIN(IF($K$2:$K$21=A10,$E$2:$E$21,1E+99),IF($L$2:$L$21=A10,$E$2:$E$21,1E+99),IF($M$2:$M$21=A10,$E$2:$E$21,1E+99)) -> 1e+99
A11: 10 | B11: 3B. Definição de Personas | C11: 9 | D11: 1 | E11: =MAX(IFERROR(VLOOKUP(K11,$A$2:$F$21,6,FALSE),0),IFERROR(VLOOKUP(L11,$A$2:$F$21,6,FALSE),0),IFERROR(VLOOKUP(M11,$A$2:$F$21,6,FALSE),0)) -> 0 | F11: =E11+D11 -> 1 | G11: =H11-D11 -> 2 | H11: =IF(O11=1E+99,$N$2,O11) -> 3 | I11: =G11-E11 -> 2 | J11: =IF(I11=0,"Sim","Não") -> Não | K11: 9 | O11: =MIN(IF($K$2:$K$21=A11,$E$2:$E$21,1E+99),IF($L$2:$L$21=A11,$E$2:$E$21,1E+99),IF($M$2:$M$21=A11,$E$2:$E$21,1E+99)) -> 1e+99
A12: 11 | B12: 3C. Jornada do Usuário | C12: 9 | D12: 2 | E12: =MAX(IFERROR(VLOOKUP(K12,$A$2:$F$21,6,FALSE),0),IFERROR(VLOOKUP(L12,$A$2:$F$21,6,FALSE),0),IFERROR(VLOOKUP(M12,$A$2:$F$21,6,FALSE),0)) -> 0 | F12: =E12+D12 -> 2 | G12: =H12-D12 -> 1 | H12: =IF(O12=1E+99,$N$2,O12) -> 3 | I12: =G12-E12 -> 1 | J12: =IF(I12=0,"Sim","Não") -> Não | K12: 9 | O12: =MIN(IF($K$2:$K$21=A12,$E$2:$E$21,1E+99),IF($L$2:$L$21=A12,$E$2:$E$21,1E+99),IF($M$2:$M$21=A12,$E$2:$E$21,1E+99)) -> 1e+99
A13: 12 | B13: 3D. UI - Interface do Usuário | C13: 9 | D13: 3 | E13: =MAX(IFERROR(VLOOKUP(K13,$A$2:$F$21,6,FALSE),0),IFERROR(VLOOKUP(L13,$A$2:$F$21,6,FALSE),0),IFERROR(VLOOKUP(M13,$A$2:$F$21,6,FALSE),0)) -> 0 | F13: =E13+D13 -> 3 | G13: =H13-D13 -> 0 | H13: =IF(O13=1E+99,$N$2,O13) -> 3 | I13: =G13-E13 -> 0 | J13: =IF(I13=0,"Sim","Não") -> Sim | K13: 9 | O13: =MIN(IF($K$2:$K$21=A13,$E$2:$E$21,1E+99),IF($L$2:$L$21=A13,$E$2:$E$21,1E+99),IF($M$2:$M$21=A13,$E$2:$E$21,1E+99)) -> 1e+99
A14: 13 | B14: 4A. Preparação do Ambiente | C14: 5 | D14: 2 | E14: =MAX(IFERROR(VLOOKUP(K14,$A$2:$F$21,6,FALSE),0),IFERROR(VLOOKUP(L14,$A$2:$F$21,6,FALSE),0),IFERROR(VLOOKUP(M14,$A$2:$F$21,6,FALSE),0)) -> 0 | F14: =E14+D14 -> 2 | G14: =H14-D14 -> 1 | H14: =IF(O14=1E+99,$N$2,O14) -> 3 | I14: =G14-E14 -> 1 | J14: =IF(I14=0,"Sim","Não") -> Não | K14: 5 | O14: =MIN(IF($K$2:$K$21=A14,$E$2:$E$21,1E+99),IF($L$2:$L$21=A14,$E$2:$E$21,1E+99),IF($M$2:$M$21=A14,$E$2:$E$21,1E+99)) -> 1e+99
A15: 14 | B15: 4B. Configuração do repositório | C15: 13 | D15: 1 | E15: =MAX(IFERROR(VLOOKUP(K15,$A$2:$F$21,6,FALSE),0),IFERROR(VLOOKUP(L15,$A$2:$F$21,6,FALSE),0),IFERROR(VLOOKUP(M15,$A$2:$F$21,6,FALSE),0)) -> 0 | F15: =E15+D15 -> 1 | G15: =H15-D15 -> 2 | H15: =IF(O15=1E+99,$N$2,O15) -> 3 | I15: =G15-E15 -> 2 | J15: =IF(I15=0,"Sim","Não") -> Não | K15: 13 | O15: =MIN(IF($K$2:$K$21=A15,$E$2:$E$21,1E+99),IF($L$2:$L$21=A15,$E$2:$E$21,1E+99),IF($M$2:$M$21=A15,$E$2:$E$21,1E+99)) -> 1e+99
A16: 15 | B16: 4C. Configuração do Banco de Dados e Nuvem | C16: 14 | D16: 3 | E16: =MAX(IFERROR(VLOOKUP(K16,$A$2:$F$21,6,FALSE),0),IFERROR(VLOOKUP(L16,$A$2:$F$21,6,FALSE),0),IFERROR(VLOOKUP(M16,$A$2:$F$21,6,FALSE),0)) -> 0 | F16: =E16+D16 -> 3 | G16: =H16-D16 -> 0 | H16: =IF(O16=1E+99,$N$2,O16) -> 3 | I16: =G16-E16 -> 0 | J16: =IF(I16=0,"Sim","Não") -> Sim | K16: 14 | O16: =MIN(IF($K$2:$K$21=A16,$E$2:$E$21,1E+99),IF($L$2:$L$21=A16,$E$2:$E$21,1E+99),IF($M$2:$M$21=A16,$E$2:$E$21,1E+99)) -> 1e+99
A17: 16 | B17: 4D. Backend | C17: 15 | D17: 3 | E17: =MAX(IFERROR(VLOOKUP(K17,$A$2:$F$21,6,FALSE),0),IFERROR(VLOOKUP(L17,$A$2:$F$21,6,FALSE),0),IFERROR(VLOOKUP(M17,$A$2:$F$21,6,FALSE),0)) -> 0 | F17: =E17+D17 -> 3 | G17: =H17-D17 -> 0 | H17: =IF(O17=1E+99,$N$2,O17) -> 3 | I17: =G17-E17 -> 0 | J17: =IF(I17=0,"Sim","Não") -> Sim | K17: 15 | O17: =MIN(IF($K$2:$K$21=A17,$E$2:$E$21,1E+99),IF($L$2:$L$21=A17,$E$2:$E$21,1E+99),IF($M$2:$M$21=A17,$E$2:$E$21,1E+99)) -> 1e+99
A18: 17 | B18: 4E. Implementação do ETL | C18: 16 | D18: 2 | E18: =MAX(IFERROR(VLOOKUP(K18,$A$2:$F$21,6,FALSE),0),IFERROR(VLOOKUP(L18,$A$2:$F$21,6,FALSE),0),IFERROR(VLOOKUP(M18,$A$2:$F$21,6,FALSE),0)) -> 0 | F18: =E18+D18 -> 2 | G18: =H18-D18 -> 1 | H18: =IF(O18=1E+99,$N$2,O18) -> 3 | I18: =G18-E18 -> 1 | J18: =IF(I18=0,"Sim","Não") -> Não | K18: 16 | O18: =MIN(IF($K$2:$K$21=A18,$E$2:$E$21,1E+99),IF($L$2:$L$21=A18,$E$2:$E$21,1E+99),IF($M$2:$M$21=A18,$E$2:$E$21,1E+99)) -> 1e+99
A19: 18 | B19: 4F. Criação de APIs de Integração | C19: 16 | D19: 3 | E19: =MAX(IFERROR(VLOOKUP(K19,$A$2:$F$21,6,FALSE),0),IFERROR(VLOOKUP(L19,$A$2:$F$21,6,FALSE),0),IFERROR(VLOOKUP(M19,$A$2:$F$21,6,FALSE),0)) -> 0 | F19: =E19+D19 -> 3 | G19: =H19-D19 -> 0 | H19: =IF(O19=1E+99,$N$2,O19) -> 3 | I19: =G19-E19 -> 0 | J19: =IF(I19=0,"Sim","Não") -> Sim | K19: 16 | O19: =MIN(IF($K$2:$K$21=A19,$E$2:$E$21,1E+99),IF($L$2:$L$21=A19,$E$2:$E$21,1E+99),IF($M$2:$M$21=A19,$E$2:$E$21,1E+99)) -> 1e+99
A20: 19 | B20: 4G. Autenticação e perfis de acesso | C20: 16 | D20: 2 | E20: =MAX(IFERROR(VLOOKUP(K20,$A$2:$F$21,6,FALSE),0),IFERROR(VLOOKUP(L20,$A$2:$F$21,6,FALSE),0),IFERROR(VLOOKUP(M20,$A$2:$F$21,6,FALSE),0)) -> 0 | F20: =E20+D20 -> 2 | G20: =H20-D20 -> 1 | H20: =IF(O20=1E+99,$N$2,O20) -> 3 | I20: =G20-E20 -> 1 | J20: =IF(I20=0,"Sim","Não") -> Não | K20: 16 | O20: =MIN(IF($K$2:$K$21=A20,$E$2:$E$21,1E+99),IF($L$2:$L$21=A20,$E$2:$E$21,1E+99),IF($M$2:$M$21=A20,$E$2:$E$21,1E+99)) -> 1e+99
A21: 20 | B21: 4H. Inteligência Artificial / Machine Learning | C21: 17 | D21: 3 | E21: =MAX(IFERROR(VLOOKUP(K21,$A$2:$F$21,6,FALSE),0),IFERROR(VLOOKUP(L21,$A$2:$F$21,6,FALSE),0),IFERROR(VLOOKUP(M21,$A$2:$F$21,6,FALSE),0)) -> 0 | F21: =E21+D21 -> 3 | G21: =H21-D21 -> 0 | H21: =IF(O21=1E+99,$N$2,O21) -> 3 | I21: =G21-E21 -> 0 | J21: =IF(I21=0,"Sim","Não") -> Sim | K21: 17 | O21: =MIN(IF($K$2:$K$21=A21,$E$2:$E$21,1E+99),IF($L$2:$L$21=A21,$E$2:$E$21,1E+99),IF($M$2:$M$21=A21,$E$2:$E$21,1E+99)) -> 1e+99

Sheet Gestão de Custo
B2: Previsões de Orçamento | J2: InovaTech
C4: 1 | D4: Capa | F4: Instruções, Histórico de Alterações e as Aprovações
C5: =C4+1 -> 2 | D5: Orçado | F5: Detalhamento dos investimentos orçados
C6: =C5+1 -> 3 | D6: Realizado | F6: Detalhamento dos investimentos realizados
C7: =C6+1 -> 4 | D7: Status | F7: Status comparando Orçado x Realizado
C8: =C7+1 -> 5 | D8: Parâmetros | F8: Parâmetros usados nas outras abas da planilha.
D10: Fonte | E10: https://escritoriodeprojetos.com.br/download/previsoes-do-orcamento/
B14: Controle de Versões
B15: Versão | C15: Data | D15: Autor | E15: Notas da Revisão
B16: 1 | C16: 45958 | D16: Bruna Lira
B17: 2 | C17: 45964 | D17: Bruna Lira
B20: Instruções | D20: =TODAY() -> 45971
B21: Ref. | C21: Aba | D21: Respons | E21: Passos
B22: 0 | C22: Param | D22: PMO | E22: Inserir o Custo de Capital e o Retorno Requerido do Investimento (ROI). Preencher também o nome do projeto (InovaTech) e o patrocinador (Cannoli).
B23: 1 | C23: Orçado | D23: Gerente de Projetos | E23: Preencher as informações de identificação: nome do projeto, solicitante e patrocinador.
B24: =B23+1 -> 2 | C24: Orçado | D24: Gerente de Projetos | E24: Inserir na coluna B o nome de cada gasto ou categoria de despesa (Infraestrutura, Desenvolvimento, Licenças, Marketing, etc.). Caso haja mais de 5 categorias, agrupar ou ajustar conforme necessário.
B25: =B24+1 -> 3 | C25: Orçado | D25: Gerente de Projetos | E25: Sempre que possível, descrever como foi calculado o valor de cada gasto (ex.: cotação, pesquisa de mercado, valor médio).
B26: =B25+1 -> 4 | C26: Orçado | D26: Gerente de Projetos | E26: Validar se todos os custos estão lançados corretamente e revisar fórmulas de soma e totalização.
B27: =B26+1 -> 5 | C27: Orçado | D27: Gerente de Projetos | E27: Preencher na coluna B o nome dos custos adicionais ou operacionais, se aplicável.
B28: =B27+1 -> 6 | C28: Orçado | D28: Gerente de Projetos | E28: Verificar se os valores orçados estão coerentes com o orçamento total disponível e atualizar caso haja revisões.
B29: =B28+1 -> 7 | C29: Orçado | D29: Gerente de Projetos | E29: Registrar os valores efetivamente realizados mês a mês. Caso não haja detalhamento, inserir o valor total do mês na linha de consolidação.
B30: =B29+1 -> 8 | C30: Realizado | D30: Gerente de Projetos | E30: Acompanhar o comparativo entre Orçado x Realizado e verificar os percentuais de desvio (%). Gráfico e cálculos são automáticos, não editar fórmulas.
B31: =B30+1 -> 9 | C31: Todos | D31: Equipe Toda | E31: Garantir que todas as abas estejam atualizadas antes das reuniões de acompanhamento mensal do projeto.
B32: =B31+1 -> 10
B33: =B32+1 -> 11
B34: =B33+1 -> 12
B36: Aprovações
B37: Ref. | C37: Data | D37: Participante | E37: Assinatura
B38: 1 | C38: 45968 | D38: Rafaela Coelho | E38: R.C
B39: 2
B40: 3

Sheet Orcado
B2: Identificação do Projeto | D2: Mês
B3: Nome do Projeto | C3: InovaTech | E3: 45870 | F3: 45909 | G3: =DATE(YEAR(F3),MONTH(F3)+1,DAY(F3)) -> 45939 | H3: =DATE(YEAR(G3),MONTH(G3)+1,DAY(G3)) -> 45970 | I3: =DATE(YEAR(H3),MONTH(H3)+1,DAY(H3)) -> 46000 | J3: =DATE(YEAR(I3),MONTH(I3)+1,DAY(I3)) -> 46031 | K3: =DATE(YEAR(J3),MONTH(J3)+1,DAY(J3)) -> 46062 | L3: =DATE(YEAR(K3),MONTH(K3)+1,DAY(K3)) -> 46090 | M3: =DATE(YEAR(L3),MONTH(L3)+1,DAY(L3)) -> 46121 | N3: =DATE(YEAR(M3),MONTH(M3)+1,DAY(M3)) -> 46151 | ... P3: =DATE(YEAR(O3),MONTH(O3)+1,DAY(O3)) -> 46212 | Q3: TOTAL
B4: Patrocinador | C4: Cannoli – Parceira Comercial | D4: 0 | E4: 1 | F4: =E4+1 -> 2 | G4: =F4+1 -> 3 | H4: =G4+1 -> 4 | I4: =H4+1 -> 5 | J4: =I4+1 -> 6 | K4: =J4+1 -> 7 | L4: =K4+1 -> 8 | M4: =L4+1 -> 9 | ... P4: =O4+1 -> 12
B5: Investimento inicial Total | C5: 184000 | D5: =SUM(D9+D11+D13+D15+D17+D19+D21+D23+D25+D27+D29) -> 183200 | E5: =SUM(E33:E46)+E9+E11+E13+E15+E17+E19+E21+E23+E25+E27+E29 -> 10888.23 | F5: =SUM(F33:F46)+F9+F11+F13+F15+F17+F19+F21+F23+F25+F27 -> 10805.458 | G5: =SUM(G33:G46)+G9+G11+G13+G15+G17+G19+G21+G23+G25+G27 -> 7986.0038 | H5: =SUM(H33:H46)+H9+H11+H13+H15+H17+H19+H21+H23+H25+H27 -> 8234.6042 | I5: =SUM(I33:I46)+I9+I11+I13+I15+I17+I19+I21+I23+I25+I27 -> 9058.0646 | J5: =SUM(J33:J46)+J9+J11+J13+J15+J17+J19+J21+J23+J25+J27 -> 9963.8711 | K5: =SUM(K33:K46)+K9+K11+K13+K15+K17+K19+K21+K23+K25+K27 -> 10960.258 | L5: =SUM(L33:L46)+L9+L11+L13+L15+L17+L19+L21+L23+L25+L27 -> 12056.284 | M5: =SUM(M33:M46)+M9+M11+M13+M15+M17+M19+M21+M23+M25+M27 -> 13261.912 | ... P5: =SUM(P33:P46)+P9+P11+P13+P15+P17+P19+P21+P23+P25+P27 -> 17651.605 | Q5: =SUM(D5:P5) -> 324701.31
B6: Investimento Acumulado | C6: 0 | D6: =D5 -> 183200 | E6: =D6+E5 -> 194088.23 | F6: =E6+F5 -> 204893.69 | G6: =F6+G5 -> 212879.69 | H6: =G6+H5 -> 221114.3 | I6: =H6+I5 -> 230172.36 | J6: =I6+J5 -> 240136.23 | K6: =J6+K5 -> 251096.49 | L6: =K6+L5 -> 263152.77 | ... P6: =O6+P5 -> 324701.31
B7: Orçado | C7: Explicação
B8: Investimento c/ taxa de crescimento | C8: Para facilitar o cálculo dos gastos do projeto InovaTech, foi aplicada uma taxa média de crescimento mensal de 10% sobre cada etapa de desenvolvimento.
B9: Planejamento e Definição do Escopo | C9: Reuniões com stakeholders da Cannoli, levantamento de requisitos e cronograma. | D9: 8000 | E9: 4000 | F9: =E9*(1+F8) -> 4000 | G9: 500 | H9: 0 | I9: =H9*(1+I8) -> 0 | J9: =I9*(1+J8) -> 0 | K9: =J9*(1+K8) -> 0 | L9: =K9*(1+L8) -> 0 | M9: =L9*(1+M8) -> 0 | N9: =M9*(1+N8) -> 0 | O9: =N9*(1+O8) -> 0 | P9: =O9*(1+P8) -> 0 | Q9: =SUM(E9:P9) -> 8500
B10: Taxa de Crescimento de 10% | C10: Taxa de crescimento de investimento de 10% ao mês MOM | F10: 0.1 | G10: =F10 -> 0.1 | H10: =G10 -> 0.1 | I10: =H10 -> 0.1 | J10: =I10 -> 0.1 | K10: =J10 -> 0.1 | L10: =K10 -> 0.1 | M10: =L10 -> 0.1 | N10: =M10 -> 0.1 | ... P10: =O10 -> 0.1
B11: Análise de Dados e Modelagem | C11: Estruturação do banco de dados, estudo das métricas e indicadores que serão exibidos. | D11: 21000 | E11: 794.96 | F11: =E11*(1+F10) -> 874.456 | G11: =F11*(1+G10) -> 961.9016 | H11: =G11*(1+H10) -> 1058.0918 | I11: =H11*(1+I10) -> 1163.9009 | J11: =I11*(1+J10) -> 1280.291 | K11: =J11*(1+K10) -> 1408.3201 | L11: =K11*(1+L10) -> 1549.1521 | M11: =L11*(1+M10) -> 1704.0674 | ... P11: =O11*(1+P10) -> 2268.1137 | Q11: =SUM(E11:P11) -> 16999.65
B12: Taxa de Crescimento de 10% | C12: Taxa de crescimento de investimento de 10% ao mês MOM | F12: 0.1 | G12: =F12 -> 0.1 | H12: =G12 -> 0.1 | I12: =H12 -> 0.1 | J12: =I12 -> 0.1 | K12: =J12 -> 0.1 | L12: =K12 -> 0.1 | M12: =L12 -> 0.1 | N12: =M12 -> 0.1 | ... P12: =O12 -> 0.1
B13: Design de Interface (UI/UX) | C13: Criação dos dashboards no Figma, escolha da paleta e layout. | D13: 13200 | E13: 617.29 | F13: =E13*(1+F12) -> 679.019 | G13: =F13*(1+G12) -> 746.9209 | H13: =G13*(1+H12) -> 821.61299 | I13: =H13*(1+I12) -> 903.77429 | J13: =I13*(1+J12) -> 994.15172 | K13: =J13*(1+K12) -> 1093.5669 | L13: =K13*(1+L12) -> 1202.9236 | M13: =L13*(1+M12) -> 1323.2159 | ... P13: =O13*(1+P12) -> 1761.2004 | Q13: =SUM(E13:P13) -> 13200.305
B14: Taxa de Crescimento de 10% | C14: Taxa de crescimento de investimento de 10% ao mês MOM | F14: 0.1 | G14: =F14 -> 0.1 | H14: =G14 -> 0.1 | I14: =H14 -> 0.1 | J14: =I14 -> 0.1 | K14: =J14 -> 0.1 | L14: =K14 -> 0.1 | M14: =L14 -> 0.1 | N14: =M14 -> 0.1 | ... P14: =O14 -> 0.1
B15: Desenvolvimento Backend e Frontend | C15: Construção da API Flask, integração com SQLite e desenvolvimento do painel web. | D15: 50000 | E15: 1496.43 | F15: =E15*(1+F14) -> 1646.073 | G15: =F15*(1+G14) -> 1810.6803 | H15: =G15*(1+H14) -> 1991.7483 | I15: =H15*(1+I14) -> 2190.9232 | J15: =I15*(1+J14) -> 2410.0155 | K15: =J15*(1+K14) -> 2651.017 | L15: =K15*(1+L14) -> 2916.1187 | M15: =L15*(1+M14) -> 3207.7306 | ... P15: =O15*(1+P14) -> 4269.4894 | Q15: =SUM(E15:P15) -> 32000.084
B16: Taxa de Crescimento de 10% | C16: Taxa de crescimento de investimento de 10% ao mês MOM | F16: 0.1 | G16: =F16 -> 0.1 | H16: =G16 -> 0.1 | I16: =H16 -> 0.1 | J16: =I16 -> 0.1 | K16: =J16 -> 0.1 | L16: =K16 -> 0.1 | M16: =L16 -> 0.1 | N16: =M16 -> 0.1 | ... P16: =O16 -> 0.1
B17: Integração de Dados da Cannoli | C17: Conexão com os dados reais da Cannoli, validação e testes de importação. | D17: 5000 | E17: 233.8 | F17: =E17*(1+F16) -> 257.18 | G17: =F17*(1+G16) -> 282.898 | H17: =G17*(1+H16) -> 311.1878 | I17: =H17*(1+I16) -> 342.30658 | J17: =I17*(1+J16) -> 376.53724 | K17: =J17*(1+K16) -> 414.19096 | L17: =K17*(1+L16) -> 455.61006 | M17: =L17*(1+M16) -> 501.17106 | ... P17: =O17*(1+P16) -> 667.05869 | Q17: =SUM(E17:P17) -> 4999.6455
B18: Taxa de Crescimento de 10% | C18: Taxa de crescimento de investimento de 10% ao mês MOM | F18: 0.1 | G18: =F18 -> 0.1 | H18: =G18 -> 0.1 | I18: =H18 -> 0.1 | J18: =I18 -> 0.1 | K18: =J18 -> 0.1 | L18: =K18 -> 0.1 | M18: =L18 -> 0.1 | N18: =M18 -> 0.1 | ... P18: =O18 -> 0.1
B19: Testes e Validação de Funcionalidades | C19: Teste de login, gráficos, relatórios e responsividade. | D19: 12000 | E19: 542.45 | F19: =E19*(1+F18) -> 596.695 | G19: =F19*(1+G18) -> 656.3645 | H19: =G19*(1+H18) -> 722.00095 | I19: =H19*(1+I18) -> 794.20105 | J19: =I19*(1+J18) -> 873.62115 | K19: =J19*(1+K18) -> 960.98326 | L19: =K19*(1+L18) -> 1057.0816 | M19: =L19*(1+M18) -> 1162.7897 | ... P19: =O19*(1+P18) -> 1547.6732 | Q19: =SUM(E19:P19) -> 11599.905
B20: Taxa de Crescimento de 10% | C20: Taxa de crescimento de investimento de 10% ao mês MOM | F20: 0.1 | G20: =F20 -> 0.1 | H20: =G20 -> 0.1 | I20: =H20 -> 0.1 | J20: =I20 -> 0.1 | K20: =J20 -> 0.1 | L20: =K20 -> 0.1 | M20: =L20 -> 0.1 | N20: =M20 -> 0.1 | ... P20: =O20 -> 0.1
B21: Apresentação para a Cannoli | C21: Entrega da primeira versão funcional e coleta de feedback. | D21: 15000 | E21: 869.8 | F21: =E21*(1+F20) -> 956.78 | G21: =F21*(1+G20) -> 1052.458 | H21: =G21*(1+H20) -> 1157.7038 | I21: =H21*(1+I20) -> 1273.4742 | J21: =I21*(1+J20) -> 1400.8216 | K21: =J21*(1+K20) -> 1540.9038 | L21: =K21*(1+L20) -> 1694.9941 | M21: =L21*(1+M20) -> 1864.4935 | ... P21: =O21*(1+P20) -> 2481.6409 | Q21: =SUM(E21:P21) -> 18600.05
B22: Taxa de Crescimento de 10% | C22: Taxa de crescimento de investimento de 10% ao mês MOM | F22: 0.1 | G22: =F22 -> 0.1 | H22: =G22 -> 0.1 | I22: =H22 -> 0.1 | J22: =I22 -> 0.1 | K22: =J22 -> 0.1 | L22: =K22 -> 0.1 | M22: =L22 -> 0.1 | N22: =M22 -> 0.1 | ... P22: =O22 -> 0.1
B23: Ajustes Pós-Feedback | C23: Correções e melhorias de interface e performance. | D23: 16000 | E23: 514.4 | F23: =E23*(1+F22) -> 565.84 | G23: =F23*(1+G22) -> 622.424 | H23: =G23*(1+H22) -> 684.6664 | I23: =H23*(1+I22) -> 753.13304 | J23: =I23*(1+J22) -> 828.44634 | K23: =J23*(1+K22) -> 911.29098 | L23: =K23*(1+L22) -> 1002.4201 | M23: =L23*(1+M22) -> 1102.6621 | ... P23: =O23*(1+P22) -> 1467.6432 | Q23: =SUM(E23:P23) -> 11000.076
B24: Taxa de Crescimento de 10% | C24: Taxa de crescimento de investimento de 10% ao mês MOM | F24: 0.1 | G24: =F24 -> 0.1 | H24: =G24 -> 0.1 | I24: =H24 -> 0.1 | J24: =I24 -> 0.1 | K24: =J24 -> 0.1 | L24: =K24 -> 0.1 | M24: =L24 -> 0.1 | N24: =M24 -> 0.1 | ... P24: =O24 -> 0.1
B25: Relatório e Demonstração Final | C25: Preparação do pitch, apresentações e entrega para banca/professor. | D25: 14000 | E25: 701.45 | F25: =E25*(1+F24) -> 771.595 | G25: =F25*(1+G24) -> 848.7545 | H25: =G25*(1+H24) -> 933.62995 | I25: =H25*(1+I24) -> 1026.9929 | J25: =I25*(1+J24) -> 1129.6922 | K25: =J25*(1+K24) -> 1242.6615 | L25: =K25*(1+L24) -> 1366.9276 | M25: =L25*(1+M24) -> 1503.6204 | ... P25: =O25*(1+P24) -> 2001.3187 | Q25: =SUM(E25:P25) -> 15000.006
B26: Taxa de Crescimento de 10% | C26: Taxa de crescimento de investimento de 10% ao mês MOM | F26: 0.1 | G26: =F26 -> 0.1 | H26: =G26 -> 0.1 | I26: =H26 -> 0.1 | J26: =I26 -> 0.1 | K26: =J26 -> 0.1 | L26: =K26 -> 0.1 | M26: =L26 -> 0.1 | N26: =M26 -> 0.1 | ... P26: =O26 -> 0.1
B27: Encerramento do Projeto | C27: Documentação final e análise dos indicadores do projeto. | D27: 9000 | E27: 416.2 | F27: =E27*(1+F26) -> 457.82 | G27: =F27*(1+G26) -> 503.602 | H27: =G27*(1+H26) -> 553.9622 | I27: =H27*(1+I26) -> 609.35842 | J27: =I27*(1+J26) -> 670.29426 | K27: =J27*(1+K26) -> 737.32369 | L27: =K27*(1+L26) -> 811.05606 | M27: =L27*(1+M26) -> 892.16166 | ... P27: =O27*(1+P26) -> 1187.4672 | Q27: =SUM(E27:P27) -> 8900.1389
B28: Taxa de Crescimento de 10% | C28: Taxa de crescimento de investimento de 10% ao mês MOM | F28: 0.1 | G28: =F28 -> 0.1 | H28: =G28 -> 0.1 | I28: =H28 -> 0.1 | J28: =I28 -> 0.1 | K28: =J28 -> 0.1 | L28: =K28 -> 0.1 | M28: =L28 -> 0.1 | N28: =M28 -> 0.1 | ... P28: =O28 -> 0.1
B29: Expansão | C29: Feedback e adapção | D29: 20000 | E29: 701.45 | F29: =E29*(1+F28) -> 771.595 | G29: =F29*(1+G28) -> 848.7545 | H29: =G29*(1+H28) -> 933.62995 | I29: =H29*(1+I28) -> 1026.9929 | J29: =I29*(1+J28) -> 1129.6922 | K29: =J29*(1+K28) -> 1242.6615 | L29: =K29*(1+L28) -> 1366.9276 | M29: =L29*(1+M28) -> 1503.6204 | ... P29: =O29*(1+P28) -> 2001.3187 | Q29: =SUM(E29:P29) -> 15000.006
B32: Investimentos
B33: Custo de Implementação | D33: 183200 | E33: 0 | F33: =E33 -> 0 | G33: =F33 -> 0 | H33: =G33 -> 0 | I33: =H33 -> 0 | J33: =I33 -> 0 | K33: =J33 -> 0 | L33: =K33 -> 0 | M33: =L33 -> 0 | ... P33: =O33 -> 0 | Q33: =SUM(D33:P33) -> 183200
B34: Custo da Operação | F34: =E34 -> 0 | G34: =F34 -> 0 | H34: =G34 -> 0 | I34: =H34 -> 0 | J34: =I34 -> 0 | K34: =J34 -> 0 | L34: =K34 -> 0 | M34: =L34 -> 0 | ... P34: =O34 -> 0 | Q34: =SUM(D34:P34) -> 0
B35: Custos de Treinamento | F35: =E35 -> 0 | G35: =F35 -> 0 | H35: =G35 -> 0 | I35: =H35 -> 0 | J35: =I35 -> 0 | K35: =J35 -> 0 | L35: =K35 -> 0 | M35: =L35 -> 0 | ... P35: =O35 -> 0 | Q35: =SUM(D35:P35) -> 0
B51: Indicadores Financeiros
B53: NPV/VPL | D53: =NPV(Param!D4,E5:P5)+D5 -> 324701.31
B54: Payback | D54: =COUNTIF(D6:P6,"<=0") -> 0
B55: ROI | D55: =SUM(E5:P5)/-D5 -> -0.77238706

Sheet Realizado
B2: =Orcado!B2 -> Identificação do Projeto | E2: Mês
B3: Nome do Projeto | C3: InovaTech – Dashboard Inteligente para a Cannoli | E3: =Orcado!E3 -> 45870 | F3: =Orcado!F3 -> 45909 | G3: =Orcado!G3 -> 45939 | H3: =Orcado!H3 -> 45970 | I3: =Orcado!I3 -> 46000 | J3: =Orcado!J3 -> 46031 | K3: 46023 | L3: =Orcado!L3 -> 46090 | M3: =Orcado!M3 -> 46121 | N3: =Orcado!N3 -> 46151 | O3: =Orcado!O3 -> 46182 | P3: =Orcado!P3 -> 46212 | Q3: TOTAL
B4: Patrocinador | C4: Cannoli – Rede de Restaurantes | D4: 0 | E4: 1 | F4: =E4+1 -> 2 | G4: =F4+1 -> 3 | H4: =G4+1 -> 4 | I4: =H4+1 -> 5 | J4: =I4+1 -> 6 | K4: =J4+1 -> 7 | L4: =K4+1 -> 8 | M4: =L4+1 -> 9 | ... P4: =O4+1 -> 12
B5: Investimento Total | D5: =SUM(D9+D11+D13+D15+D17+D19+D21+D23+D25+D27+D29) -> 168500 | E5: =SUM(E39:E52)+E9+E11+E13+E15+E17+E19+E21+E23+E25+E27+E29 -> 7987.4 | F5: =SUM(F9+F11+F13+F15+F17+F19+F21+F23+F25+F27+F29) -> 8708.14 | G5: =SUM(G9+G11+G13+G15+G17+G19+G21+G23+G25+G27+G29) -> 9500.954 | H5: =SUM(H9+H11+H13+H15+H17+H19+H21+H23+H25+H27+H29) -> 10373.049 | I5: =SUM(I9+I11+I13+I15+I17+I19+I21+I23+I25+I27+I29) -> 11332.354 | J5: =SUM(J9+J11+J13+J15+J17+J19+J21+J23+J25+J27+J29) -> 12387.59 | K5: =SUM(K9+K11+K13+K15+K17+K19+K21+K23+K25+K27+K29) -> 13548.349 | L5: =SUM(L9+L11+L13+L15+L17+L19+L21+L23+L25+L27+L29) -> 14825.184 | M5: =SUM(M9+M11+M13+M15+M17+M19+M21+M23+M25+M27+M29) -> 16229.702 | ... P5: =SUM(P9+P11+P13+P15+P17+P19+P21+P23+P25+P27+P29) -> 21343.553 | Q5: =SUM(E5:P5) -> 163485.09
B6: Investimento Acumulado | D6: =D5 -> 168500 | E6: =D6+E5 -> 176487.4 | F6: =E6+F5 -> 185195.54 | G6: =F6+G5 -> 194696.49 | H6: =G6+H5 -> 205069.54 | I6: =H6+I5 -> 216401.9 | J6: =I6+J5 -> 228789.49 | K6: =J6+K5 -> 242337.84 | L6: =K6+L5 -> 257163.02 | ... P6: =O6+P5 -> 331985.09
B7: Realizado | C7: Explicação
B8: Investimento c/ taxa de crescimento
B9: =Orcado!B9 -> Planejamento e Definição do Escopo | C9: Reuniões concluídas com stakeholders da Cannoli, levantamento de requisitos finalizado e escopo aprovado. | D9: 8500 | E9: 780 | F9: =E9*(1+F8) -> 780 | G9: =F9*(1+G8) -> 780 | H9: =G9*(1+H8) -> 780 | I9: =H9*(1+I8) -> 780 | J9: =I9*(1+J8) -> 780 | K9: =J9*(1+K8) -> 780 | L9: =K9*(1+L8) -> 780 | M9: =L9*(1+M8) -> 780 | ... P9: =O9*(1+P8) -> 780 | Q9: =SUM(E9:P9) -> 9360
F10: 0.1 | G10: 0.1 | H10: 0.1 | I10: 0.1 | J10: 0.1 | K10: 0.1 | L10: 0.1 | M10: 0.1 | N10: 0.1 | O10: 0.1 | P10: 0.1
B11: =Orcado!B11 -> Análise de Dados e Modelagem | C11: Banco de dados estruturado, métricas definidas e primeiros testes de extração concluídos. | D11: 20300 | E11: 780 | F11: =E11*(1+F10) -> 858 | G11: =F11*(1+G10) -> 943.8 | H11: =G11*(1+H10) -> 1038.18 | I11: =H11*(1+I10) -> 1141.998 | J11: =I11*(1+J10) -> 1256.1978 | K11: =J11*(1+K10) -> 1381.8176 | L11: =K11*(1+L10) -> 1519.9993 | M11: =L11*(1+M10) -> 1671.9993 | ... P11: =O11*(1+P10) -> 2225.431 | Q11: =SUM(E11:P11) -> 16679.741
F12: 0.1 | G12: =F12 -> 0.1 | H12: =G12 -> 0.1 | I12: =H12 -> 0.1 | J12: =I12 -> 0.1 | K12: =J12 -> 0.1 | L12: =K12 -> 0.1 | M12: =L12 -> 0.1 | N12: =M12 -> 0.1 | ... P12: =O12 -> 0.1
B13: =Orcado!B13 -> Design de Interface (UI/UX) | C13: Protótipo dos dashboards finalizado no Figma e validado pela equipe; layout aprovado. | D13: 13900 | E13: 700 | F13: =E13*(1+F12) -> 770 | G13: =F13*(1+G12) -> 847 | H13: =G13*(1+H12) -> 931.7 | I13: =H13*(1+I12) -> 1024.87 | J13: =I13*(1+J12) -> 1127.357 | K13: =J13*(1+K12) -> 1240.0927 | L13: =K13*(1+L12) -> 1364.102 | M13: =L13*(1+M12) -> 1500.5122 | ... P13: =O13*(1+P12) -> 1997.1817 | Q13: =SUM(E13:P13) -> 14968.999
F14: 0.1 | G14: =F14 -> 0.1 | H14: =G14 -> 0.1 | I14: =H14 -> 0.1 | J14: =I14 -> 0.1 | K14: =J14 -> 0.1 | L14: =K14 -> 0.1 | M14: =L14 -> 0.1 | N14: =M14 -> 0.1 | ... P14: =O14 -> 0.1
B15: =Orcado!B15 -> Desenvolvimento Backend e Frontend | C15: API Flask concluída, integração com SQLite implementada e painel web funcional. | D15: 52000 | E15: 1700 | F15: =E15*(1+F14) -> 1870 | G15: =F15*(1+G14) -> 2057 | H15: =G15*(1+H14) -> 2262.7 | I15: =H15*(1+I14) -> 2488.97 | J15: =I15*(1+J14) -> 2737.867 | K15: =J15*(1+K14) -> 3011.6537 | L15: =K15*(1+L14) -> 3312.8191 | M15: =L15*(1+M14) -> 3644.101 | ... P15: =O15*(1+P14) -> 4850.2984 | Q15: =SUM(E15:P15) -> 36353.282
F16: 0.1 | G16: =F16 -> 0.1 | H16: =G16 -> 0.1 | I16: =H16 -> 0.1 | J16: =I16 -> 0.1 | K16: =J16 -> 0.1 | L16: =K16 -> 0.1 | M16: =L16 -> 0.1 | N16: =M16 -> 0.1 | ... P16: =O16 -> 0.1
B17: =Orcado!B17 -> Integração de Dados da Cannoli | C17: Conexão com dados reais da Cannoli estabelecida, testes de importação e segurança executados. | D17: 4500 | E17: 203 | F17: =E17*(1+F16) -> 223.3 | G17: =F17*(1+G16) -> 245.63 | H17: =G17*(1+H16) -> 270.193 | I17: =H17*(1+I16) -> 297.2123 | J17: =I17*(1+J16) -> 326.93353 | K17: =J17*(1+K16) -> 359.62688 | L17: =K17*(1+L16) -> 395.58957 | M17: =L17*(1+M16) -> 435.14853 | ... P17: =O17*(1+P16) -> 579.18269 | Q17: =SUM(E17:P17) -> 4341.0096
F18: 0.1 | G18: =F18 -> 0.1 | H18: =G18 -> 0.1 | I18: =H18 -> 0.1 | J18: =I18 -> 0.1 | K18: =J18 -> 0.1 | L18: =K18 -> 0.1 | M18: =L18 -> 0.1 | N18: =M18 -> 0.1 | ... P18: =O18 -> 0.1
B19: =Orcado!B19 -> Testes e Validação de Funcionalidades | C19: Testes de login, gráficos e relatórios realizados com sucesso; bugs críticos corrigidos. | D19: 11600 | E19: 520 | F19: =E19*(1+F18) -> 572 | G19: =F19*(1+G18) -> 629.2 | H19: =G19*(1+H18) -> 692.12 | I19: =H19*(1+I18) -> 761.332 | J19: =I19*(1+J18) -> 837.4652 | K19: =J19*(1+K18) -> 921.21172 | L19: =K19*(1+L18) -> 1013.3329 | M19: =L19*(1+M18) -> 1114.6662 | ... P19: =O19*(1+P18) -> 1483.6207 | Q19: =SUM(E19:P19) -> 11119.828
F20: 0.1 | G20: =F20 -> 0.1 | H20: =G20 -> 0.1 | I20: =H20 -> 0.1 | J20: =I20 -> 0.1 | K20: =J20 -> 0.1 | L20: =K20 -> 0.1 | M20: =L20 -> 0.1 | N20: =M20 -> 0.1 | ... P20: =O20 -> 0.1
B21: =Orcado!B21 -> Apresentação para a Cannoli | C21: Primeira versão entregue e feedback documentado para ajustes e melhorias. | D21: 14500 | E21: 950 | F21: =E21*(1+F20) -> 1045 | G21: =F21*(1+G20) -> 1149.5 | H21: =G21*(1+H20) -> 1264.45 | I21: =H21*(1+I20) -> 1390.895 | J21: =I21*(1+J20) -> 1529.9845 | K21: =J21*(1+K20) -> 1682.983 | L21: =K21*(1+L20) -> 1851.2812 | M21: =L21*(1+M20) -> 2036.4094 | ... P21: =O21*(1+P20) -> 2710.4609 | Q21: =SUM(E21:P21) -> 20315.07
F22: 0.1 | G22: =F22 -> 0.1 | H22: =G22 -> 0.1 | I22: =H22 -> 0.1 | J22: =I22 -> 0.1 | K22: =J22 -> 0.1 | L22: =K22 -> 0.1 | M22: =L22 -> 0.1 | N22: =M22 -> 0.1 | ... P22: =O22 -> 0.1
B23: =Orcado!B23 -> Ajustes Pós-Feedback | C23: Melhorias aplicadas com base no retorno da Cannoli; desempenho otimizado. | D23: 16000 | E23: 514.4 | F23: =E23*(1+F22) -> 565.84 | G23: =F23*(1+G22) -> 622.424 | H23: =G23*(1+H22) -> 684.6664 | I23: =H23*(1+I22) -> 753.13304 | J23: =I23*(1+J22) -> 828.44634 | K23: =J23*(1+K22) -> 911.29098 | L23: =K23*(1+L22) -> 1002.4201 | M23: =L23*(1+M22) -> 1102.6621 | ... P23: =O23*(1+P22) -> 1467.6432 | Q23: =SUM(E23:P23) -> 11000.076
F24: 0.1 | G24: =F24 -> 0.1 | H24: =G24 -> 0.1 | I24: =H24 -> 0.1 | J24: =I24 -> 0.1 | K24: =J24 -> 0.1 | L24: =K24 -> 0.1 | M24: =L24 -> 0.1 | N24: =M24 -> 0.1 | ... P24: =O24 -> 0.1
B25: =Orcado!B25 -> Relatório e Demonstração Final | C25: Relatório de resultados e apresentação final elaborados e entregues para a banca. | D25: 11600 | E25: 720 | F25: =E25*(1+F24) -> 792 | G25: =F25*(1+G24) -> 871.2 | H25: =G25*(1+H24) -> 958.32 | I25: =H25*(1+I24) -> 1054.152 | J25: =I25*(1+J24) -> 1159.5672 | K25: =J25*(1+K24) -> 1275.5239 | L25: =K25*(1+L24) -> 1403.0763 | M25: =L25*(1+M24) -> 1543.3839 | ... P25: =O25*(1+P24) -> 2054.244 | Q25: =SUM(E25:P25) -> 15396.684
F26: 0.1 | G26: =F26 -> 0.1 | H26: =G26 -> 0.1 | I26: =H26 -> 0.1 | J26: =I26 -> 0.1 | K26: =J26 -> 0.1 | L26: =K26 -> 0.1 | M26: =L26 -> 0.1 | N26: =M26 -> 0.1 | ... P26: =O26 -> 0.1
B27: =Orcado!B27 -> Encerramento do Projeto | C27: Documentação técnica e financeira concluída; indicadores de sucesso registrados. | D27: 6000 | E27: 410 | F27: =E27*(1+F26) -> 451 | G27: =F27*(1+G26) -> 496.1 | H27: =G27*(1+H26) -> 545.71 | I27: =H27*(1+I26) -> 600.281 | J27: =I27*(1+J26) -> 660.3091 | K27: =J27*(1+K26) -> 726.34001 | L27: =K27*(1+L26) -> 798.97401 | M27: =L27*(1+M26) -> 878.87141 | ... P27: =O27*(1+P26) -> 1169.7778 | Q27: =SUM(E27:P27) -> 8767.5563
F28: 0.1 | G28: =F28 -> 0.1 | H28: =G28 -> 0.1 | I28: =H28 -> 0.1 | J28: =I28 -> 0.1 | K28: =J28 -> 0.1 | L28: =K28 -> 0.1 | M28: =L28 -> 0.1 | N28: =M28 -> 0.1 | ... P28: =O28 -> 0.1
B29: =Orcado!B29 -> Expansão | C29: Planejamento de possíveis novas integrações e versões futuras da plataforma. | D29: 9600 | E29: 710 | F29: =E29*(1+F28) -> 781 | G29: =F29*(1+G28) -> 859.1 | H29: =G29*(1+H28) -> 945.01 | I29: =H29*(1+I28) -> 1039.511 | J29: =I29*(1+J28) -> 1143.4621 | K29: =J29*(1+K28) -> 1257.8083 | L29: =K29*(1+L28) -> 1383.5891 | M29: =L29*(1+M28) -> 1521.9481 | ... P29: =O29*(1+P28) -> 2025.7129 | Q29: =SUM(E29:P29) -> 15182.841
B38: Investimentos
B39: =Orcado!B33 -> Custo de Implementação | D39: 160800 | E39: 0 | F39: =E39 -> 0 | G39: =F39 -> 0 | H39: =G39 -> 0 | I39: =H39 -> 0 | J39: =I39 -> 0 | K39: =J39 -> 0 | L39: =K39 -> 0 | M39: =L39 -> 0 | ... P39: =O39 -> 0 | Q39: =SUM(D39:P39) -> 160800
B40: =Orcado!B34 -> Custo da Operação | F40: =E40 -> 0 | G40: =F40 -> 0 | H40: =G40 -> 0 | I40: =H40 -> 0 | J40: =I40 -> 0 | K40: =J40 -> 0 | L40: =K40 -> 0 | M40: =L40 -> 0 | ... P40: =O40 -> 0 | Q40: =SUM(D40:P40) -> 0
B41: =Orcado!B35 -> Custos de Treinamento | F41: =E41 -> 0 | G41: =F41 -> 0 | H41: =G41 -> 0 | I41: =H41 -> 0 | J41: =I41 -> 0 | K41: =J41 -> 0 | L41: =K41 -> 0 | M41: =L41 -> 0 | ... P41: =O41 -> 0 | Q41: =SUM(D41:P41) -> 0
B57: Indicadores Financeiros
B59: NPV/VPL | D59: =NPV(Param!D4,E5:P5)+D5 -> 331985.09
B60: Payback | D60: =COUNTIF(D6:P6,"<=0") -> 0
B61: ROI | D61: =SUM(E5:P5)/-D5 -> -0.9702379

Sheet Gráfico -Status
B2: Períodos | C2: No Período (R$) | E2: Acumulado (R$) | G2: Desvio (R$) | H2: Desvio %
B3: Mês | C3: Orçado | D3: Realizado | E3: Orçado | F3: Realizado | G3: Diferença dos realizados
B4: 0 | C4: =HLOOKUP($B4,Orcado!$D$4:$P$5,2,FALSE) -> 183200 | D4: =HLOOKUP($B4,Realizado!$D$4:$P$5,2,FALSE) -> 168500 | E4: =C4 -> 183200 | F4: =D4 -> 168500 | G4: =F4-E4 -> -14700 | H4: =IF(E4=0,"",F4/E4-1) -> -0.080240175
B5: =B4+1 -> 1 | C5: =HLOOKUP($B5,Orcado!$D$4:$P$5,2,FALSE) -> 10888.23 | D5: =HLOOKUP($B5,Realizado!$D$4:$P$5,2,FALSE) -> 7987.4 | E5: =E4+C5 -> 194088.23 | F5: =F4+D5 -> 176487.4 | G5: =F5-E5 -> -17600.83 | H5: =F5/E5-1 -> -0.090684685
B6: =B5+1 -> 2 | C6: =HLOOKUP($B6,Orcado!$D$4:$P$5,2,FALSE) -> 10805.458 | D6: =HLOOKUP($B6,Realizado!$D$4:$P$5,2,FALSE) -> 8708.14 | E6: =E5+C6 -> 204893.69 | F6: =F5+D6 -> 185195.54 | G6: =F6-E6 -> -19698.148 | H6: =F6/E6-1 -> -0.096138384
B7: =B6+1 -> 3 | C7: =HLOOKUP($B7,Orcado!$D$4:$P$5,2,FALSE) -> 7986.0038 | D7: =HLOOKUP($B7,Realizado!$D$4:$P$5,2,FALSE) -> 9500.954 | E7: =E6+C7 -> 212879.69 | F7: =F6+D7 -> 194696.49 | G7: =F7-E7 -> -18183.198 | H7: =F7/E7-1 -> -0.085415371
B8: =B7+1 -> 4 | C8: =HLOOKUP($B8,Orcado!$D$4:$P$5,2,FALSE) -> 8234.6042 | D8: =HLOOKUP($B8,Realizado!$D$4:$P$5,2,FALSE) -> 10373.049 | E8: =E7+C8 -> 221114.3 | F8: =F7+D8 -> 205069.54 | G8: =F8-E8 -> -16044.753 | H8: =F8/E8-1 -> -0.072563162
B9: =B8+1 -> 5 | C9: =HLOOKUP($B9,Orcado!$D$4:$P$5,2,FALSE) -> 9058.0646 | D9: =HLOOKUP($B9,Realizado!$D$4:$P$5,2,FALSE) -> 11332.354 | E9: =E8+C9 -> 230172.36 | F9: =F8+D9 -> 216401.9 | G9: =F9-E9 -> -13770.463 | H9: =F9/E9-1 -> -0.059826744
B10: =B9+1 -> 6 | C10: =HLOOKUP($B10,Orcado!$D$4:$P$5,2,FALSE) -> 9963.8711 | D10: =HLOOKUP($B10,Realizado!$D$4:$P$5,2,FALSE) -> 12387.59 | E10: =E9+C10 -> 240136.23 | F10: =F9+D10 -> 228789.49 | G10: =F10-E10 -> -11346.744 | H10: =F10/E10-1 -> -0.047251279
B11: =B10+1 -> 7 | C11: =HLOOKUP($B11,Orcado!$D$4:$P$5,2,FALSE) -> 10960.258 | D11: =HLOOKUP($B11,Realizado!$D$4:$P$5,2,FALSE) -> 13548.349 | E11: =E10+C11 -> 251096.49 | F11: =F10+D11 -> 242337.84 | G11: =F11-E11 -> -8758.6535 | H11: =F11/E11-1 -> -0.034881625
B12: =B11+1 -> 8 | C12: =HLOOKUP($B12,Orcado!$D$4:$P$5,2,FALSE) -> 12056.284 | D12: =HLOOKUP($B12,Realizado!$D$4:$P$5,2,FALSE) -> 14825.184 | E12: =E11+C12 -> 263152.77 | F12: =F11+D12 -> 257163.02 | G12: =F12-E12 -> -5989.7539 | H12: =F12/E12-1 -> -0.022761508
B13: =B12+1 -> 9 | C13: =HLOOKUP($B13,Orcado!$D$4:$P$5,2,FALSE) -> 13261.912 | D13: =HLOOKUP($B13,Realizado!$D$4:$P$5,2,FALSE) -> 16229.702 | E13: =E12+C13 -> 276414.69 | F13: =F12+D13 -> 273392.72 | G13: =F13-E13 -> -3021.9643 | H13: =F13/E13-1 -> -0.01093272
B14: =B13+1 -> 10 | C14: =HLOOKUP($B14,Orcado!$D$4:$P$5,2,FALSE) -> 14588.104 | D14: =HLOOKUP($B14,Realizado!$D$4:$P$5,2,FALSE) -> 17774.672 | E14: =E13+C14 -> 291002.79 | F14: =F13+D14 -> 291167.39 | G14: =F14-E14 -> 164.6043 | H14: =F14/E14-1 -> 0.00056564508
B15: =B14+1 -> 11 | C15: =HLOOKUP($B15,Orcado!$D$4:$P$5,2,FALSE) -> 16046.914 | D15: =HLOOKUP($B15,Realizado!$D$4:$P$5,2,FALSE) -> 19474.139 | E15: =E14+C15 -> 307049.7 | F15: =F14+D15 -> 310641.53 | G15: =F15-E15 -> 3591.8297 | H15: =F15/E15-1 -> 0.011697877
B16: =B15+1 -> 12 | C16: =HLOOKUP($B16,Orcado!$D$4:$P$5,2,FALSE) -> 17651.605 | D16: =HLOOKUP($B16,Realizado!$D$4:$P$5,2,FALSE) -> 21343.553 | E16: =E15+C16 -> 324701.31 | F16: =F15+D16 -> 331985.09 | G16: =F16-E16 -> 7283.7777 | H16: =F16/E16-1 -> 0.02243224
B17: Total | C17: =SUM(C4:C16) -> 324701.31 | D17: =SUM(D4:D16) -> 331985.09
B18: Saldo Final | C18: =C17-D17 -> -7283.7777
I19: Variação de +2% indica equilíbrio e eficiência na execução orçamentária do InovaTech.
B21: Ao longo da execução do projeto InovaTech, observou-se uma variação gradual entre os valores orçados e realizados.
B22: Nos primeiros meses, o investimento real ficou abaixo do planejado devido à otimização de recursos e à adoção de ferramentas gratuitas (como Flask e SQLite).
B23: Entretanto, a partir da fase de integração e ajustes pós-feedback, houve um aumento de custos relacionado à ampliação das funcionalidades e à melhoria da experiência do usuário.
B25: No encerramento do projeto, o investimento total apresentou um desvio positivo de apenas 2%, mantendo-se dentro da margem de tolerância prevista para projetos de inovação.
B26: Esse resultado reflete uma gestão financeira eficiente, com controle de custos, boa alocação de recursos e decisões estratégicas baseadas em valor agregado.

Sheet Param
B2: Variável | C2: Tipo de Benefício | D2: Custo do Capital | E2: 184000
B3: Explicação | D3: Retorno Requerido do Investimento | E3: 0.08
B4: Domínio ou Valor | C4: Aumento de Receita com base em decisões estratégicas mais assertivas
C5: Aumento de Produtividade das equipes de gestão da Cannoli
C6: Melhoria na Tomada de Decisão baseada em dados reais
C7: Redução de Retrabalho operacional e tempo de análise manual
C8: Redução dos Custos com campanhas ineficientes
C9: Aumento da Satisfação dos clientes finais
C10: Aumento da Fidelização e do Ticket Médio
C11: Melhoria do Controle Financeiro e de Vendas
B15: Parametros a serem configurados inicialmente
B16: Projeto
B17: Nome do projeto | C17: InovaTech – Dashboard Inteligente para a Cannoli
B18: Mês de início | C18: 45870
B19: Patrocinador | C19: Cannoli – Rede de Restaurantes
B20: Gerente de Projeto | C20: Bruna Lira e Rafela Coelho
B21: 0

Sheet Capa
B5: Informações sobre o projeto
B6: Projeto | E6: InovaTech – Dashboard Inteligente
B7: Gerente Responsável | E7: Bruna Lira e Rafaela Coelho
B8: Data da avaliação | E8: 45969
B9: Histórico da avaliação de riscos
B10: 45884 | C10: Início do levantamento preliminar de riscos do projeto InovaTech, com foco em definir escopo e identificar possíveis gargalos técnicos.
B11: 45912 | C11: Segunda avaliação realizada após a definição dos requisitos e arquitetura do sistema. Foram identificados novos riscos ligados à integração de dados e prazos de desenvolvimento.
B12: 45945 | C12: Reavaliação dos riscos durante o desenvolvimento do back-end. Ajustes realizados nos planos de mitigação e priorização dos riscos mais críticos.
B13: 45969 | C13: Etapa final de revisão dos riscos, contemplando as fases de testes, implantação e entrega final do InovaTech Dashboard.

Sheet Identificar
A1: Identificação dos Riscos | AF1: Probabilidade | AI1: Impacto
A4: =Capa!E6 -> InovaTech – Dashboard Inteligente
AF5: Muito Baixa - 1 | AG5: 1 | AI5: Muito Baixo - 1 | AJ5: 1
A6: ID | B6: Fase ou | D6: Declaração do Risco | G6: Resp. | H6: Estratégia de Resposta | I6: Plano de Prevenção | J6: Plano de Contingência | L6: Severidade (X,Y) | AF6: Baixa - 2 | AG6: 2 | AI6: Muito Baixo - 2 | AJ6: 2
B7: Recurso | C7: Classificação | D7: CAUSA | E7: RISCO | F7: CONSEQUÊNCIA | K7: Riscos Colaterais | AF7: Moderada - 3 | AG7: 3 | AI7: Baixo - 3 | AJ7: 3
A8: R01 | B8: Pessoas | C8: Disponibilidade | D8: Como resultado de sobrecarga de tarefas da equipe técnica. | E8: Pode ocorrer atraso na entrega dos módulos principais. | F8: O cronograma geral do projeto pode ser impactado. | G8: Bruna | H8: Mitigar | I8: Replanejar atividades e dividir tarefas entre os membros. | J8: Redirecionar tarefas prioritárias e ajustar cronograma. | K8: Atraso no projeto e aumento nos custos | L8: 0.08 | AF8: Alta - 4 | AG8: 4 | AI8: Baixo - 4 | AJ8: 4
A9: R02 | B9: Técnica | C9: Falta de habilidade | D9: Como resultado de incompatibilidade entre o banco de dados e as APIs de coleta. | E9: Pode ocorrer falha na consolidação dos dados de vendas e clientes. | F9: As análises e relatórios podem apresentar informações incorretas. | G9: Rafaela | H9: Mitigar | I9: Realizar testes de integração com dados simulados antes da implantação. | J9: Corrigir scripts de integração e restaurar backup anterior. | L9: 0.04
A10: R03 | B10: Escopo | C10: Expectativas | D10: Como resultado de mudanças solicitadas pelo cliente (Cannoli) após início do desenvolvimento. | E10: Pode ocorrer aumento de esforço e retrabalho. | F10: O custo e o prazo do projeto podem ser ampliados. | G10: Bruna | H10: Evitar | I10: Validar requisitos com o cliente antes de iniciar o desenvolvimento. | J10: Avaliar impacto e renegociar escopo. | L10: 0.08
A11: R04 | B11: Segurança | C11: Roubos | D11: Como resultado de falhas de autenticação ou vazamento de informações. | E11: Pode ocorrer comprometimento da privacidade dos dados. | F11: O projeto pode sofrer sanções relacionadas à LGPD. | G11: Rafaela | H11: Mitigar | I11: Implementar controle de acesso e criptografia. | J11: Desativar sistema temporariamente e revisar logs de acesso. | L11: 0.04
A12: R05 | B12: Operacional | C12: Quebras | D12: Como resultado de falha no servidor local ou ambiente de hospedagem. | E12: Pode ocorrer indisponibilidade temporária do dashboard. | F12: A coleta de dados e a visualização de métricas podem ser interrompidas. | G12: Bruna | H12: Transferir | I12: Utilizar backup automático e hospedagem em ambiente redundante. | J12: Migrar sistema para servidor de contingência. | L12: 0.08
A13: R06 | B13: Qualidade | C13: Defeito | D13: Como resultado de ausência de testes automatizados e revisões de código. | E13: Pode ocorrer falha na funcionalidade de KPIs e relatórios. | F13: A confiabilidade dos indicadores pode ser comprometida. | G13: Rafaela | H13: Mitigar | I13: Adotar testes unitários e revisões de código entre pares. | J13: Corrigir bugs detectados após implantação e emitir patch corretivo. | L13: 0.04
A14: R07 | L14: =Qualificar!K14
A15: R08 | L15: =Qualificar!K15
A16: R09
A17: R10
A18: R11
A19: R12
A20: R13
A21: R14
A22: R15
A23: R16
A24: R17
A25: R18
A26: R19 | L26: =Qualificar!K26
A27: R20 | L27: =Qualificar!K27

Sheet Qualificar
A1: Qualificação dos Riscos | AF1: Probabilidade | AI1: Impacto
K2: Base Custo | M2: 8000 | N2: R$
K3: Base Prazo | M3: 30 | N3: dias úteis
A4: =Identificar!A4 -> InovaTech – Dashboard Inteligente
AF5: Muito Baixa - 1 | AG5: 1 | AI5: Muito Baixo - 1 | AJ5: 1
A6: ID | B6: Declaração do Risco | E6: Resp. | F6: Probabilidade do risco virar incidente (Y) | G6: Avaliação de Impacto (X) | K6: Severidade (Y,X) | M6: Custo | N6: Prazo | AF6: Baixa - 2 | AG6: 2 | AI6: Muito Baixo - 2 | AJ6: 2
B7: CAUSA (Começa a frase com "Como Resultado ...") | C7: RISCO (Começar a frase com "Pode ocorrer ...") | D7: CONSEQÜÊNCIA (Começar a frase com "O que acarretaria ...") | G7: Aumento no Custo (X1) | H7: Desvio no Cronograma (X2) | I7: (X1*X2) | J7: Resultado do Impacto (X1+X2) | L7: Riscos Colaterais | AF7: Moderada - 3 | AG7: 3 | AI7: Baixo - 3 | AJ7: 3
A8: =IF(Identificar!A8<>"",Identificar!A8,"") -> R01 | B8: =IF(Identificar!D8<>"",Identificar!D8,"") -> Como resultado de sobrecarga de tarefas da equipe técnica. | C8: =IF(Identificar!E8<>"",Identificar!E8,"") -> Pode ocorrer atraso na entrega dos módulos principais. | D8: =IF(Identificar!F8<>"",Identificar!F8,"") -> O cronograma geral do projeto pode ser impactado. | E8: =IF(Identificar!G8<>"",Identificar!G8,"") -> Bruna | F8: Alta - 0,4 | G8: Entre 10% e 20% - 1,40 | H8: Insignificante - 2,05 | I8: =IF(G8<>"",IF(H8<>"",RIGHT(G8,4)*RIGHT(H8,4),""),"") -> 2.87 | J8: =IF(I8<>"",VLOOKUP(I8,'Sensibilidade ao Risco'!$E$2:$F$30,2,FALSE),"") -> Moderada - 0,20 | K8: =IF(F8<>"",IF(J8<>"",(RIGHT(J8,3))*(RIGHT(F8,3)),""),"") -> 0.08 | L8: Atraso no projeto e aumento nos custos | M8: =ROUNDUP(Quantificar!G8/Qualificar!$M$2,2) -> 1 | N8: =ROUNDUP(Quantificar!H8/Qualificar!$M$3,2) -> 0.17 | AF8: Alta - 4 | AG8: 4 | AI8: Baixo - 4 | AJ8: 4
A9: =IF(Identificar!A9<>"",Identificar!A9,"") -> R02 | B9: =IF(Identificar!D9<>"",Identificar!D9,"") -> Como resultado de incompatibilidade entre o banco de dados e as APIs de coleta. | C9: =IF(Identificar!E9<>"",Identificar!E9,"") -> Pode ocorrer falha na consolidação dos dados de vendas e clientes. | D9: =IF(Identificar!F9<>"",Identificar!F9,"") -> As análises e relatórios podem apresentar informações incorretas. | E9: =IF(Identificar!G9<>"",Identificar!G9,"") -> Rafaela | F9: Muito baixa - 0,05 | G9: Maior que 20% - 1,80 | H9: Entre 5% e 10% - 2,20 | I9: =IF(G9<>"",IF(H9<>"",RIGHT(G9,4)*RIGHT(H9,4),""),"") -> 3.96 | J9: =IF(I9<>"",VLOOKUP(I9,'Sensibilidade ao Risco'!$E$2:$F$30,2,FALSE),"") -> Muito Alta - 0,80 | K9: =IF(F9<>"",IF(J9<>"",(RIGHT(J9,3))*(RIGHT(F9,3)),""),"") -> 0.04 | M9: =ROUNDUP(Quantificar!G9/Qualificar!$M$2,2) -> 0.5 | N9: =ROUNDUP(Quantificar!H9/Qualificar!$M$3,2) -> 0.17
A10: =IF(Identificar!A10<>"",Identificar!A10,"") -> R03 | B10: =IF(Identificar!D10<>"",Identificar!D10,"") -> Como resultado de mudanças solicitadas pelo cliente (Cannoli) após início do desenvolvimento. | C10: =IF(Identificar!E10<>"",Identificar!E10,"") -> Pode ocorrer aumento de esforço e retrabalho. | D10: =IF(Identificar!F10<>"",Identificar!F10,"") -> O custo e o prazo do projeto podem ser ampliados. | E10: =IF(Identificar!G10<>"",Identificar!G10,"") -> Bruna | F10: Moderada - 0,2 | G10: Entre 10% e 20% - 1,40 | H10: Entre 10% e 20% - 2,40 | I10: =IF(G10<>"",IF(H10<>"",RIGHT(G10,4)*RIGHT(H10,4),""),"") -> 3.36 | J10: =IF(I10<>"",VLOOKUP(I10,'Sensibilidade ao Risco'!$E$2:$F$30,2,FALSE),"") -> Muito Alta - 0,80 | K10: =IF(F10<>"",IF(J10<>"",(RIGHT(J10,3))*(RIGHT(F10,3)),""),"") -> 0.16 | M10: =ROUNDUP(Quantificar!G10/Qualificar!$M$2,2) -> 5 | N10: =ROUNDUP(Quantificar!H10/Qualificar!$M$3,2) -> 1
A11: =IF(Identificar!A11<>"",Identificar!A11,"") -> R04 | B11: =IF(Identificar!D11<>"",Identificar!D11,"") -> Como resultado de falhas de autenticação ou vazamento de informações. | C11: =IF(Identificar!E11<>"",Identificar!E11,"") -> Pode ocorrer comprometimento da privacidade dos dados. | D11: =IF(Identificar!F11<>"",Identificar!F11,"") -> O projeto pode sofrer sanções relacionadas à LGPD. | E11: =IF(Identificar!G11<>"",Identificar!G11,"") -> Rafaela | F11: Baixa - 0,1 | G11: Entre 5% e 10% - 1,20 | H11: Entre 10% e 20% - 2,40 | I11: =IF(G11<>"",IF(H11<>"",RIGHT(G11,4)*RIGHT(H11,4),""),"") -> 2.88 | J11: =IF(I11<>"",VLOOKUP(I11,'Sensibilidade ao Risco'!$E$2:$F$30,2,FALSE),"") -> Alta - 0,40 | K11: =IF(F11<>"",IF(J11<>"",(RIGHT(J11,3))*(RIGHT(F11,3)),""),"") -> 0.04 | M11: =ROUNDUP(Quantificar!G11/Qualificar!$M$2,2) -> 1 | N11: =ROUNDUP(Quantificar!H11/Qualificar!$M$3,2) -> 0.17
A12: =IF(Identificar!A12<>"",Identificar!A12,"") -> R05 | B12: =IF(Identificar!D12<>"",Identificar!D12,"") -> Como resultado de falha no servidor local ou ambiente de hospedagem. | C12: =IF(Identificar!E12<>"",Identificar!E12,"") -> Pode ocorrer indisponibilidade temporária do dashboard. | D12: =IF(Identificar!F12<>"",Identificar!F12,"") -> A coleta de dados e a visualização de métricas podem ser interrompidas. | E12: =IF(Identificar!G12<>"",Identificar!G12,"") -> Bruna | F12: Alta - 0,4 | G12: Entre 5% e 10% - 1,20 | H12: Menor que 5% - 2,10 | I12: =IF(G12<>"",IF(H12<>"",RIGHT(G12,4)*RIGHT(H12,4),""),"") -> 2.52 | J12: =IF(I12<>"",VLOOKUP(I12,'Sensibilidade ao Risco'!$E$2:$F$30,2,FALSE),"") -> Moderada - 0,20 | K12: =IF(F12<>"",IF(J12<>"",(RIGHT(J12,3))*(RIGHT(F12,3)),""),"") -> 0.08 | M12: =ROUNDUP(Quantificar!G12/Qualificar!$M$2,2) -> 1 | N12: =ROUNDUP(Quantificar!H12/Qualificar!$M$3,2) -> 0.17
A13: =IF(Identificar!A13<>"",Identificar!A13,"") -> R06 | B13: =IF(Identificar!D13<>"",Identificar!D13,"") -> Como resultado de ausência de testes automatizados e revisões de código. | C13: =IF(Identificar!E13<>"",Identificar!E13,"") -> Pode ocorrer falha na funcionalidade de KPIs e relatórios. | D13: =IF(Identificar!F13<>"",Identificar!F13,"") -> A confiabilidade dos indicadores pode ser comprometida. | E13: =IF(Identificar!G13<>"",Identificar!G13,"") -> Rafaela | F13: Alta - 0,4 | G13: Menos de 5% - 1,10 | H13: Menor que 5% - 2,10 | I13: =IF(G13<>"",IF(H13<>"",RIGHT(G13,4)*RIGHT(H13,4),""),"") -> 2.31 | J13: =IF(I13<>"",VLOOKUP(I13,'Sensibilidade ao Risco'!$E$2:$F$30,2,FALSE),"") -> Baixa - 0,10 | K13: =IF(F13<>"",IF(J13<>"",(RIGHT(J13,3))*(RIGHT(F13,3)),""),"") -> 0.04 | M13: =ROUNDUP(Quantificar!G13/Qualificar!$M$2,2) -> 0.63 | N13: =ROUNDUP(Quantificar!H13/Qualificar!$M$3,2) -> 0.17
A14: =IF(Identificar!A14<>"",Identificar!A14,"") -> R07 | B14: =IF(Identificar!D14<>"",Identificar!D14,"") | C14: =IF(Identificar!E14<>"",Identificar!E14,"") | D14: =IF(Identificar!F14<>"",Identificar!F14,"") | E14: =IF(Identificar!G14<>"",Identificar!G14,"") | I14: =IF(G14<>"",IF(H14<>"",RIGHT(G14,4)*RIGHT(H14,4),""),"") | J14: =IF(I14<>"",VLOOKUP(I14,'Sensibilidade ao Risco'!$E$2:$F$30,2,FALSE),"") | K14: =IF(F14<>"",IF(J14<>"",(RIGHT(J14,3))*(RIGHT(F14,3)),""),"") | M14: =ROUNDUP(Quantificar!G14/Qualificar!$M$2,2) -> 0 | N14: =ROUNDUP(Quantificar!H14/Qualificar!$M$3,2) -> 0
A15: =IF(Identificar!A15<>"",Identificar!A15,"") -> R08 | B15: =IF(Identificar!D15<>"",Identificar!D15,"") | C15: =IF(Identificar!E15<>"",Identificar!E15,"") | D15: =IF(Identificar!F15<>"",Identificar!F15,"") | E15: =IF(Identificar!G15<>"",Identificar!G15,"") | I15: =IF(G15<>"",IF(H15<>"",RIGHT(G15,4)*RIGHT(H15,4),""),"") | J15: =IF(I15<>"",VLOOKUP(I15,'Sensibilidade ao Risco'!$E$2:$F$30,2,FALSE),"") | K15: =IF(F15<>"",IF(J15<>"",(RIGHT(J15,3))*(RIGHT(F15,3)),""),"") | M15: =ROUNDUP(Quantificar!G15/Qualificar!$M$2,2) -> 0 | N15: =ROUNDUP(Quantificar!H15/Qualificar!$M$3,2) -> 0
A16: =IF(Identificar!A16<>"",Identificar!A16,"") -> R09 | B16: =IF(Identificar!D16<>"",Identificar!D16,"") | C16: =IF(Identificar!E16<>"",Identificar!E16,"") | D16: =IF(Identificar!F16<>"",Identificar!F16,"") | E16: =IF(Identificar!G16<>"",Identificar!G16,"") | I16: =IF(G16<>"",IF(H16<>"",RIGHT(G16,4)*RIGHT(H16,4),""),"") | J16: =IF(I16<>"",VLOOKUP(I16,'Sensibilidade ao Risco'!$E$2:$F$30,2,FALSE),"") | K16: =IF(F16<>"",IF(J16<>"",(RIGHT(J16,3))*(RIGHT(F16,3)),""),"") | M16: =ROUNDUP(Quantificar!G16/Qualificar!$M$2,2) -> 0 | N16: =ROUNDUP(Quantificar!H16/Qualificar!$M$3,2) -> 0
A17: =IF(Identificar!A17<>"",Identificar!A17,"") -> R10 | B17: =IF(Identificar!D17<>"",Identificar!D17,"") | C17: =IF(Identificar!E17<>"",Identificar!E17,"") | D17: =IF(Identificar!F17<>"",Identificar!F17,"") | E17: =IF(Identificar!G17<>"",Identificar!G17,"") | I17: =IF(G17<>"",IF(H17<>"",RIGHT(G17,4)*RIGHT(H17,4),""),"") | J17: =IF(I17<>"",VLOOKUP(I17,'Sensibilidade ao Risco'!$E$2:$F$30,2,FALSE),"") | K17: =IF(F17<>"",IF(J17<>"",(RIGHT(J17,3))*(RIGHT(F17,3)),""),"") | M17: =ROUNDUP(Quantificar!G17/Qualificar!$M$2,2) -> 0 | N17: =ROUNDUP(Quantificar!H17/Qualificar!$M$3,2) -> 0
A18: =IF(Identificar!A18<>"",Identificar!A18,"") -> R11 | B18: =IF(Identificar!D18<>"",Identificar!D18,"") | C18: =IF(Identificar!E18<>"",Identificar!E18,"") | D18: =IF(Identificar!F18<>"",Identificar!F18,"") | E18: =IF(Identificar!G18<>"",Identificar!G18,"") | I18: =IF(G18<>"",IF(H18<>"",RIGHT(G18,4)*RIGHT(H18,4),""),"") | J18: =IF(I18<>"",VLOOKUP(I18,'Sensibilidade ao Risco'!$E$2:$F$30,2,FALSE),"") | K18: =IF(F18<>"",IF(J18<>"",(RIGHT(J18,3))*(RIGHT(F18,3)),""),"") | M18: =ROUNDUP(Quantificar!G18/Qualificar!$M$2,2) -> 0 | N18: =ROUNDUP(Quantificar!H18/Qualificar!$M$3,2) -> 0
A19: =IF(Identificar!A19<>"",Identificar!A19,"") -> R12 | B19: =IF(Identificar!D19<>"",Identificar!D19,"") | C19: =IF(Identificar!E19<>"",Identificar!E19,"") | D19: =IF(Identificar!F19<>"",Identificar!F19,"") | E19: =IF(Identificar!G19<>"",Identificar!G19,"") | I19: =IF(G19<>"",IF(H19<>"",RIGHT(G19,4)*RIGHT(H19,4),""),"") | J19: =IF(I19<>"",VLOOKUP(I19,'Sensibilidade ao Risco'!$E$2:$F$30,2,FALSE),"") | K19: =IF(F19<>"",IF(J19<>"",(RIGHT(J19,3))*(RIGHT(F19,3)),""),"") | M19: =ROUNDUP(Quantificar!G19/Qualificar!$M$2,2) -> 0 | N19: =ROUNDUP(Quantificar!H19/Qualificar!$M$3,2) -> 0
A20: =IF(Identificar!A20<>"",Identificar!A20,"") -> R13 | B20: =IF(Identificar!D20<>"",Identificar!D20,"") | C20: =IF(Identificar!E20<>"",Identificar!E20,"") | D20: =IF(Identificar!F20<>"",Identificar!F20,"") | E20: =IF(Identificar!G20<>"",Identificar!G20,"") | I20: =IF(G20<>"",IF(H20<>"",RIGHT(G20,4)*RIGHT(H20,4),""),"") | J20: =IF(I20<>"",VLOOKUP(I20,'Sensibilidade ao Risco'!$E$2:$F$30,2,FALSE),"") | K20: =IF(F20<>"",IF(J20<>"",(RIGHT(J20,3))*(RIGHT(F20,3)),""),"") | M20: =ROUNDUP(Quantificar!G20/Qualificar!$M$2,2) -> 0 | N20: =ROUNDUP(Quantificar!H20/Qualificar!$M$3,2) -> 0
A21: =IF(Identificar!A21<>"",Identificar!A21,"") -> R14 | B21: =IF(Identificar!D21<>"",Identificar!D21,"") | C21: =IF(Identificar!E21<>"",Identificar!E21,"") | D21: =IF(Identificar!F21<>"",Identificar!F21,"") | E21: =IF(Identificar!G21<>"",Identificar!G21,"") | I21: =IF(G21<>"",IF(H21<>"",RIGHT(G21,4)*RIGHT(H21,4),""),"") | J21: =IF(I21<>"",VLOOKUP(I21,'Sensibilidade ao Risco'!$E$2:$F$30,2,FALSE),"") | K21: =IF(F21<>"",IF(J21<>"",(RIGHT(J21,3))*(RIGHT(F21,3)),""),"") | M21: =ROUNDUP(Quantificar!G21/Qualificar!$M$2,2) -> 0 | N21: =ROUNDUP(Quantificar!H21/Qualificar!$M$3,2) -> 0
A22: =IF(Identificar!A22<>"",Identificar!A22,"") -> R15 | B22: =IF(Identificar!D22<>"",Identificar!D22,"") | C22: =IF(Identificar!E22<>"",Identificar!E22,"") | D22: =IF(Identificar!F22<>"",Identificar!F22,"") | E22: =IF(Identificar!G22<>"",Identificar!G22,"") | I22: =IF(G22<>"",IF(H22<>"",RIGHT(G22,4)*RIGHT(H22,4),""),"") | J22: =IF(I22<>"",VLOOKUP(I22,'Sensibilidade ao Risco'!$E$2:$F$30,2,FALSE),"") | K22: =IF(F22<>"",IF(J22<>"",(RIGHT(J22,3))*(RIGHT(F22,3)),""),"") | M22: =ROUNDUP(Quantificar!G22/Qualificar!$M$2,2) -> 0 | N22: =ROUNDUP(Quantificar!H22/Qualificar!$M$3,2) -> 0
A23: =IF(Identificar!A23<>"",Identificar!A23,"") -> R16 | B23: =IF(Identificar!D23<>"",Identificar!D23,"") | C23: =IF(Identificar!E23<>"",Identificar!E23,"") | D23: =IF(Identificar!F23<>"",Identificar!F23,"") | E23: =IF(Identificar!G23<>"",Identificar!G23,"") | I23: =IF(G23<>"",IF(H23<>"",RIGHT(G23,4)*RIGHT(H23,4),""),"") | J23: =IF(I23<>"",VLOOKUP(I23,'Sensibilidade ao Risco'!$E$2:$F$30,2,FALSE),"") | K23: =IF(F23<>"",IF(J23<>"",(RIGHT(J23,3))*(RIGHT(F23,3)),""),"") | M23: =ROUNDUP(Quantificar!G23/Qualificar!$M$2,2) -> 0 | N23: =ROUNDUP(Quantificar!H23/Qualificar!$M$3,2) -> 0
A24: =IF(Identificar!A24<>"",Identificar!A24,"") -> R17 | B24: =IF(Identificar!D24<>"",Identificar!D24,"") | C24: =IF(Identificar!E24<>"",Identificar!E24,"") | D24: =IF(Identificar!F24<>"",Identificar!F24,"") | E24: =IF(Identificar!G24<>"",Identificar!G24,"") | I24: =IF(G24<>"",IF(H24<>"",RIGHT(G24,4)*RIGHT(H24,4),""),"") | J24: =IF(I24<>"",VLOOKUP(I24,'Sensibilidade ao Risco'!$E$2:$F$30,2,FALSE),"") | K24: =IF(F24<>"",IF(J24<>"",(RIGHT(J24,3))*(RIGHT(F24,3)),""),"") | M24: =ROUNDUP(Quantificar!G24/Qualificar!$M$2,2) -> 0 | N24: =ROUNDUP(Quantificar!H24/Qualificar!$M$3,2) -> 0
A25: =IF(Identificar!A25<>"",Identificar!A25,"") -> R18 | B25: =IF(Identificar!D25<>"",Identificar!D25,"") | C25: =IF(Identificar!E25<>"",Identificar!E25,"") | D25: =IF(Identificar!F25<>"",Identificar!F25,"") | E25: =IF(Identificar!G25<>"",Identificar!G25,"") | I25: =IF(G25<>"",IF(H25<>"",RIGHT(G25,4)*RIGHT(H25,4),""),"") | J25: =IF(I25<>"",VLOOKUP(I25,'Sensibilidade ao Risco'!$E$2:$F$30,2,FALSE),"") | K25: =IF(F25<>"",IF(J25<>"",(RIGHT(J25,3))*(RIGHT(F25,3)),""),"") | M25: =ROUNDUP(Quantificar!G25/Qualificar!$M$2,2) -> 0 | N25: =ROUNDUP(Quantificar!H25/Qualificar!$M$3,2) -> 0
... A27: =IF(Identificar!A27<>"",Identificar!A27,"") -> R20 | B27: =IF(Identificar!D27<>"",Identificar!D27,"") | C27: =IF(Identificar!E27<>"",Identificar!E27,"") | D27: =IF(Identificar!F27<>"",Identificar!F27,"") | E27: =IF(Identificar!G27<>"",Identificar!G27,"") | I27: =IF(G27<>"",IF(H27<>"",RIGHT(G27,4)*RIGHT(H27,4),""),"") | J27: =IF(I27<>"",VLOOKUP(I27,'Sensibilidade ao Risco'!$E$2:$F$30,2,FALSE),"") | K27: =IF(F27<>"",IF(J27<>"",(RIGHT(J27,3))*(RIGHT(F27,3)),""),"") | M27: =ROUNDUP(Quantificar!G27/Qualificar!$M$2,2) -> 0 | N27: =ROUNDUP(Quantificar!H27/Qualificar!$M$3,2) -> 0
F48: Insignificante - 1,05 | G48: Insignificante - 2,05 | H48: Muito baixa - 0,05
F49: Menor que 5% - 1,10 | G49: Menor que 5% - 2,10 | H49: Baixa - 0,1
F50: Entre 5% e 10% - 1,20 | G50: Entre 5% e 10% - 2,20 | H50: Moderada - 0,2
F51: Entre 10% e 20% - 1,40 | G51: Entre 10% e 20% - 2,40 | H51: Alta - 0,4
F52: Maior que 20% - 1,80 | G52: Maior que 20% - 2,80 | H52: Muito Alta - 0,8

Sheet Quantificar
A1: Quantificação dos Riscos | AB1: Probabilidade | AE1: Impacto
A4: =Identificar!A4 -> InovaTech – Dashboard Inteligente
AB5: Muito Baixa - 1 | AC5: 1 | AE5: Muito Baixo - 1 | AF5: 1
A6: ID | B6: Declaração do Risco | E6: Resp. | G6: Impacto no Custo | H6: Impacto no Cronograma (Colocar qtde. de dias de redução ou atraso no cronograma) | I6: Observação | J6: Plano de Prevenção | K6: Plano de Contingência | AB6: Baixa - 2 | AC6: 2 | AE6: Muito Baixo - 2 | AF6: 2
B7: CAUSA (Começa a frase com "Como Resultado ...") | C7: RISCO (Começar a frase com "Pode ocorrer ...") | D7: CONSEQÜÊNCIA (Começar a frase com "O que acarretaria ...") | F7: Riscos Colaterais | AB7: Moderada - 3 | AC7: 3 | AE7: Baixo - 3 | AF7: 3
A8: =IF(Identificar!A8<>"",Identificar!A8,"") -> R01 | B8: =IF(Identificar!D8<>"",Identificar!D8,"") -> Como resultado de sobrecarga de tarefas da equipe técnica. | C8: =IF(Identificar!E8<>"",Identificar!E8,"") -> Pode ocorrer atraso na entrega dos módulos principais. | D8: =IF(Identificar!F8<>"",Identificar!F8,"") -> O cronograma geral do projeto pode ser impactado. | E8: =IF(Identificar!G8<>"",Identificar!G8,"") -> Bruna | F8: Atraso no projeto e aumento nos custos | G8: 8000 | H8: 5 | I8: Dias de atraso na implantação | J8: =Identificar!I8 -> Replanejar atividades e dividir tarefas entre os membros. | K8: =Identificar!J8 -> Redirecionar tarefas prioritárias e ajustar cronograma. | AB8: Alta - 4 | AC8: 4 | AE8: Baixo - 4 | AF8: 4
A9: =IF(Identificar!A9<>"",Identificar!A9,"") -> R02 | B9: =IF(Identificar!D9<>"",Identificar!D9,"") -> Como resultado de incompatibilidade entre o banco de dados e as APIs de coleta. | C9: =IF(Identificar!E9<>"",Identificar!E9,"") -> Pode ocorrer falha na consolidação dos dados de vendas e clientes. | D9: =IF(Identificar!F9<>"",Identificar!F9,"") -> As análises e relatórios podem apresentar informações incorretas. | E9: =IF(Identificar!G9<>"",Identificar!G9,"") -> Rafaela | F9: Falha na integração de dados e retrabalho técnico. | G9: 4000 | H9: 5 | I9: Dias de atraso na implantação | J9: =Identificar!I9 -> Realizar testes de integração com dados simulados antes da implantação. | K9: =Identificar!J9 -> Corrigir scripts de integração e restaurar backup anterior.
A10: =IF(Identificar!A10<>"",Identificar!A10,"") -> R03 | B10: =IF(Identificar!D10<>"",Identificar!D10,"") -> Como resultado de mudanças solicitadas pelo cliente (Cannoli) após início do desenvolvimento. | C10: =IF(Identificar!E10<>"",Identificar!E10,"") -> Pode ocorrer aumento de esforço e retrabalho. | D10: =IF(Identificar!F10<>"",Identificar!F10,"") -> O custo e o prazo do projeto podem ser ampliados. | E10: =IF(Identificar!G10<>"",Identificar!G10,"") -> Bruna | F10: Replanejamento completo do cronograma e aumento de despesas. | G10: 40000 | H10: 30 | I10: 1 mês de atraso | J10: =Identificar!I10 -> Validar requisitos com o cliente antes de iniciar o desenvolvimento. | K10: =Identificar!J10 -> Avaliar impacto e renegociar escopo.
A11: =IF(Identificar!A11<>"",Identificar!A11,"") -> R04 | B11: =IF(Identificar!D11<>"",Identificar!D11,"") -> Como resultado de falhas de autenticação ou vazamento de informações. | C11: =IF(Identificar!E11<>"",Identificar!E11,"") -> Pode ocorrer comprometimento da privacidade dos dados. | D11: =IF(Identificar!F11<>"",Identificar!F11,"") -> O projeto pode sofrer sanções relacionadas à LGPD. | E11: =IF(Identificar!G11<>"",Identificar!G11,"") -> Rafaela | F11: Interrupção temporária do sistema e exposição de dados sensíveis. | G11: 8000 | H11: 5 | I11: Dias de atraso na implantação | J11: =Identificar!I11 -> Implementar controle de acesso e criptografia. | K11: =Identificar!J11 -> Desativar sistema temporariamente e revisar logs de acesso.
A12: =IF(Identificar!A12<>"",Identificar!A12,"") -> R05 | B12: =IF(Identificar!D12<>"",Identificar!D12,"") -> Como resultado de falha no servidor local ou ambiente de hospedagem. | C12: =IF(Identificar!E12<>"",Identificar!E12,"") -> Pode ocorrer indisponibilidade temporária do dashboard. | D12: =IF(Identificar!F12<>"",Identificar!F12,"") -> A coleta de dados e a visualização de métricas podem ser interrompidas. | E12: =IF(Identificar!G12<>"",Identificar!G12,"") -> Bruna | F12: Parada na coleta de dados e indisponibilidade do dashboard. | G12: 8000 | H12: 5 | I12: Dias de atraso na implantação | J12: =Identificar!I12 -> Utilizar backup automático e hospedagem em ambiente redundante. | K12: =Identificar!J12 -> Migrar sistema para servidor de contingência.
A13: =IF(Identificar!A13<>"",Identificar!A13,"") -> R06 | B13: =IF(Identificar!D13<>"",Identificar!D13,"") -> Como resultado de ausência de testes automatizados e revisões de código. | C13: =IF(Identificar!E13<>"",Identificar!E13,"") -> Pode ocorrer falha na funcionalidade de KPIs e relatórios. | D13: =IF(Identificar!F13<>"",Identificar!F13,"") -> A confiabilidade dos indicadores pode ser comprometida. | E13: =IF(Identificar!G13<>"",Identificar!G13,"") -> Rafaela | F13: Retrabalho de código e atraso na entrega final. | G13: 5000 | H13: 5 | I13: Dias de atraso na implantação | J13: =Identificar!I13 -> Adotar testes unitários e revisões de código entre pares. | K13: =Identificar!J13 -> Corrigir bugs detectados após implantação e emitir patch corretivo.
A14: =IF(Identificar!A14<>"",Identificar!A14,"") -> R07 | B14: =IF(Identificar!D14<>"",Identificar!D14,"") | C14: =IF(Identificar!E14<>"",Identificar!E14,"") | D14: =IF(Identificar!F14<>"",Identificar!F14,"") | E14: =IF(Identificar!G14<>"",Identificar!G14,"") | G14: 0 | H14: 0 | J14: =Identificar!I14 -> 0 | K14: =Identificar!J14 -> 0
A15: =IF(Identificar!A15<>"",Identificar!A15,"") -> R08 | B15: =IF(Identificar!D15<>"",Identificar!D15,"") | C15: =IF(Identificar!E15<>"",Identificar!E15,"") | D15: =IF(Identificar!F15<>"",Identificar!F15,"") | E15: =IF(Identificar!G15<>"",Identificar!G15,"") | G15: 0 | H15: 0 | J15: =Identificar!I15 -> 0 | K15: =Identificar!J15 -> 0
A16: =IF(Identificar!A16<>"",Identificar!A16,"") -> R09 | B16: =IF(Identificar!D16<>"",Identificar!D16,"") | C16: =IF(Identificar!E16<>"",Identificar!E16,"") | D16: =IF(Identificar!F16<>"",Identificar!F16,"") | E16: =IF(Identificar!G16<>"",Identificar!G16,"") | J16: =Identificar!I16 -> 0 | K16: =Identificar!J16 -> 0
A17: =IF(Identificar!A17<>"",Identificar!A17,"") -> R10 | B17: =IF(Identificar!D17<>"",Identificar!D17,"") | C17: =IF(Identificar!E17<>"",Identificar!E17,"") | D17: =IF(Identificar!F17<>"",Identificar!F17,"") | E17: =IF(Identificar!G17<>"",Identificar!G17,"") | J17: =Identificar!I17 -> 0 | K17: =Identificar!J17 -> 0
A18: =IF(Identificar!A18<>"",Identificar!A18,"") -> R11 | B18: =IF(Identificar!D18<>"",Identificar!D18,"") | C18: =IF(Identificar!E18<>"",Identificar!E18,"") | D18: =IF(Identificar!F18<>"",Identificar!F18,"") | E18: =IF(Identificar!G18<>"",Identificar!G18,"") | J18: =Identificar!I18 -> 0 | K18: =Identificar!J18 -> 0
A19: =IF(Identificar!A19<>"",Identificar!A19,"") -> R12 | B19: =IF(Identificar!D19<>"",Identificar!D19,"") | C19: =IF(Identificar!E19<>"",Identificar!E19,"") | D19: =IF(Identificar!F19<>"",Identificar!F19,"") | E19: =IF(Identificar!G19<>"",Identificar!G19,"") | J19: =Identificar!I19 -> 0 | K19: =Identificar!J19 -> 0
A20: =IF(Identificar!A20<>"",Identificar!A20,"") -> R13 | B20: =IF(Identificar!D20<>"",Identificar!D20,"") | C20: =IF(Identificar!E20<>"",Identificar!E20,"") | D20: =IF(Identificar!F20<>"",Identificar!F20,"") | E20: =IF(Identificar!G20<>"",Identificar!G20,"") | J20: =Identificar!I20 -> 0 | K20: =Identificar!J20 -> 0
A21: =IF(Identificar!A21<>"",Identificar!A21,"") -> R14 | B21: =IF(Identificar!D21<>"",Identificar!D21,"") | C21: =IF(Identificar!E21<>"",Identificar!E21,"") | D21: =IF(Identificar!F21<>"",Identificar!F21,"") | E21: =IF(Identificar!G21<>"",Identificar!G21,"") | J21: =Identificar!I21 -> 0 | K21: =Identificar!J21 -> 0
A22: =IF(Identificar!A22<>"",Identificar!A22,"") -> R15 | B22: =IF(Identificar!D22<>"",Identificar!D22,"") | C22: =IF(Identificar!E22<>"",Identificar!E22,"") | D22: =IF(Identificar!F22<>"",Identificar!F22,"") | E22: =IF(Identificar!G22<>"",Identificar!G22,"") | J22: =Identificar!I22 -> 0 | K22: =Identificar!J22 -> 0
A23: =IF(Identificar!A23<>"",Identificar!A23,"") -> R16 | B23: =IF(Identificar!D23<>"",Identificar!D23,"") | C23: =IF(Identificar!E23<>"",Identificar!E23,"") | D23: =IF(Identificar!F23<>"",Identificar!F23,"") | E23: =IF(Identificar!G23<>"",Identificar!G23,"") | J23: =Identificar!I23 -> 0 | K23: =Identificar!J23 -> 0
A24: =IF(Identificar!A24<>"",Identificar!A24,"") -> R17 | B24: =IF(Identificar!D24<>"",Identificar!D24,"") | C24: =IF(Identificar!E24<>"",Identificar!E24,"") | D24: =IF(Identificar!F24<>"",Identificar!F24,"") | E24: =IF(Identificar!G24<>"",Identificar!G24,"") | J24: =Identificar!I24 -> 0 | K24: =Identificar!J24 -> 0
A25: =IF(Identificar!A25<>"",Identificar!A25,"") -> R18 | B25: =IF(Identificar!D25<>"",Identificar!D25,"") | C25: =IF(Identificar!E25<>"",Identificar!E25,"") | D25: =IF(Identificar!F25<>"",Identificar!F25,"") | E25: =IF(Identificar!G25<>"",Identificar!G25,"") | J25: =Identificar!I25 -> 0 | K25: =Identificar!J25 -> 0
A26: =IF(Identificar!A26<>"",Identificar!A26,"") -> R19 | B26: =IF(Identificar!D26<>"",Identificar!D26,"") | C26: =IF(Identificar!E26<>"",Identificar!E26,"") | D26: =IF(Identificar!F26<>"",Identificar!F26,"") | E26: =IF(Identificar!G26<>"",Identificar!G26,"") | J26: =Identificar!I26 -> 0 | K26: =Identificar!J26 -> 0
A27: =IF(Identificar!A27<>"",Identificar!A27,"") -> R20 | B27: =IF(Identificar!D27<>"",Identificar!D27,"") | C27: =IF(Identificar!E27<>"",Identificar!E27,"") | D27: =IF(Identificar!F27<>"",Identificar!F27,"") | E27: =IF(Identificar!G27<>"",Identificar!G27,"") | J27: =Identificar!I27 -> 0 | K27: =Identificar!J27 -> 0
... A29: =IF(Identificar!A29<>"",Identificar!A29,"") | B29: =IF(Identificar!D29<>"",Identificar!D29,"") | C29: =IF(Identificar!E29<>"",Identificar!E29,"") | D29: =IF(Identificar!F29<>"",Identificar!F29,"") | E29: =IF(Identificar!G29<>"",Identificar!G29,"") | J29: =Identificar!I29 -> 0 | K29: =Identificar!J29 -> 0

Sheet Sensibilidade ao Risco
A1: Custo | B1: Peso1 | C1: Cronograma | D1: Peso2 | E1: Peso1 X Peso2 | F1: Impacto
A2: Aumento de custo Insignificante | B2: 1.05 | C2: Desvio no cronograma insignificante | D2: 2.05 | E2: =B2*D2 -> 2.1525 | F2: Muito baixa - 0,05
A3: Aumento de custo Insignificante | B3: 1.05 | C3: Desvio menor que 5% no cronograma | D3: 2.1 | E3: =B3*D3 -> 2.205 | F3: Baixa - 0,10
A4: Aumento de custo Insignificante | B4: 1.05 | C4: Desvio total entre 5% e 10% no cronograma | D4: 2.2 | E4: =B4*D4 -> 2.31 | F4: Baixa - 0,10
A5: Aumento de custo Insignificante | B5: 1.05 | C5: Desvio total entre 10% e 20% no cronograma | D5: 2.4 | E5: =B5*D5 -> 2.52 | F5: Moderada - 0,20
A6: Aumento de custo Insignificante | B6: 1.05 | C6: Desvio total maior que 20% no cronograma | D6: 2.8 | E6: =B6*D6 -> 2.94 | F6: Alta - 0,40
A8: Menos de 5% de aumento no custo | B8: 1.1 | C8: Desvio no cronograma insignificante | D8: 2.05 | E8: =B8*D8 -> 2.255 | F8: Baixa - 0,10
A9: Menos de 5% de aumento no custo | B9: 1.1 | C9: Desvio menor que 5% no cronograma | D9: 2.1 | E9: =B9*D9 -> 2.31 | F9: Baixa - 0,10
A10: Menos de 5% de aumento no custo | B10: 1.1 | C10: Desvio total entre 5% e 10% no cronograma | D10: 2.2 | E10: =B10*D10 -> 2.42 | F10: Moderada - 0,20
A11: Menos de 5% de aumento no custo | B11: 1.1 | C11: Desvio total entre 10% e 20% no cronograma | D11: 2.4 | E11: =B11*D11 -> 2.64 | F11: Alta - 0,40
A12: Menos de 5% de aumento no custo | B12: 1.1 | C12: Desvio total maior que 20% no cronograma | D12: 2.8 | E12: =B12*D12 -> 3.08 | F12: Alta - 0,40
A14: entre 5% e 10% de aumento do custo | B14: 1.2 | C14: Desvio no cronograma insignificante | D14: 2.05 | E14: =B14*D14 -> 2.46 | F14: Moderada - 0,20
A15: entre 5% e 10% de aumento do custo | B15: 1.2 | C15: Desvio menor que 5% no cronograma | D15: 2.1 | E15: =B15*D15 -> 2.52 | F15: Moderada - 0,20
... A30: Mais de 20% de aumento nos custos | B30: 1.8 | C30: Desvio total maior que 20% no cronograma | D30: 2.8 | E30: =B30*D30 -> 5.04 | F30: Muito Alta - 0,80
A31: Muito baixa - 0,05
A32: Baixa - 0,10
A33: Moderada - 0,20
A34: Alta - 0,40
A35: Muito Alta - 0,80

Sheet Plano de Comunicação
A1: 1. Identificação das principais partes interessadas no projeto (stakeholders do projeto)
A3: Quadro 01. Matriz Interesse versus Poder para o projeto
A11: Identificação Stakeholder | B11: Nível de Interesse no projeto | C11: Nível de poder no projeto | D11: Explicar a ação a ser tomada: | G11: Plano de Comunicação
A12: Empresa Parceira – Cannoli (Gestores e Representantes) | B12: Altíssimo – buscam otimizar o controle e entendimento dos dados de vendas e desempenho. | C12: Alto – definem diretrizes, aprovam entregas e fornecem acesso aos dados reais. | D12: Participar das reuniões de alinhamento, validar relatórios e sugerir melhorias no dashboard. | G12: Data: 24/10/2025 Projeto: InovaTech | O12: Página: 01/01
A13: Gerente de Projeto (Bruna Lira) | B13: Alto – responsável por coordenar a equipe e garantir a entrega dentro dos prazos e requisitos. | C13: Alto – supervisiona o progresso, distribui tarefas e comunica decisões importantes. | D13: Liderar o time, monitorar as etapas e assegurar a comunicação com todos os stakeholders.
A14: Equipe de Desenvolvimento (Back-end e Front-end) | B14: Alto – responsáveis pela construção técnica do dashboard e integração com o sistema da Cannoli. | C14: Médio – seu desempenho impacta diretamente a qualidade e funcionalidade do produto final. | D14: Implementar códigos, realizar testes e corrigir erros técnicos. | G14: Ref | H14: Atividade | I14: Assunto/Conteúdo | J14: Tipo | K14: Emissor –responsavel | L14: Local | M14: Receptor | N14: Data ou Freqüência | P14: Feedback | S14: Data Feedback | X14: Obs
A15: Equipe de Dados e Análise (BI) | B15: Alto – interessados em garantir a precisão dos dados e a clareza das visualizações. | C15: Médio – influenciam diretamente na confiabilidade e no valor estratégico do sistema. | D15: Criar consultas, validar métricas e montar relatórios analíticos. | G15: STK-001 | H15: Reunião de Abertura do Projeto | I15: Apresentação do InovaTech, definição de escopo, cronograma e responsabilidades. | J15: Reunião Presencial / Online | K15: Gerente de Projeto (Bruna Lira) | L15: Google Meet / Sede Cannoli | M15: Equipe InovaTech e Representantes da Cannoli | N15: Início do Projeto | P15: Confirmação de entendimento do escopo e das metas. | S15: Após 2 semanas | X15: Documento de abertura registrado no Drive.
A16: Equipe de Design e UX (Experiência do Usuário) | B16: Médio – foco na aparência e na usabilidade do dashboard. | C16: Médio – interferem na aceitação e facilidade de uso pelos gestores da Cannoli. | D16: Desenvolver telas intuitivas, aplicar testes de usabilidade e ajustar conforme feedbacks. | G16: STK-002 | H16: Planejamento Técnico | I16: Detalhamento da arquitetura do dashboard e definição de integrações com o sistema Cannoli. | J16: Reunião Técnica | K16: Equipe de Desenvolvimento | L16: Sala de Reunião / Meet | M16: Product Owner | N16: Quinzenal | P16: Feedback sobre viabilidade técnica e prazos. | S16: Imediatamente após cada reunião | X16: Atualização no cronograma e replanejamento se necessário.
A17: Professores Orientadores e Avaliadores | B17: Médio – interessados no desenvolvimento acadêmico e no cumprimento das entregas. | C17: Alto – avaliam, orientam e aprovam o andamento do projeto. | D17: Fornecer feedbacks, validar entregas e acompanhar a evolução do grupo | G17: STK-003 | H17: Daily Meeting | I17: Acompanhamento do progresso, identificação de impedimentos e alinhamento rápido. | J17: Reunião Online Curta | K17: Responsável: Scrum Master | L17: Meeting | M17: Desenvolvedores | N17: Diariamente | P17: Atualização sobre andamento das tarefas. | S17: Durante as reuniões diárias | X17: Registro no canal do grupo (WhatsApp ou Teams).
A18: Usuários Internos da Cannoli (Setor Administrativo e Vendas) | B18: Alto – utilizarão o dashboard no dia a dia para análise de resultados e metas. | C18: Médio – influenciam o sucesso através do uso prático e retorno de experiência. | D18: Testar o sistema, relatar dificuldades e sugerir melhorias. | G18: STK-004 | H18: Reunião de Validação com a Cannoli | I18: Apresentação das telas e análises parciais desenvolvidas. | J18: Reunião de Validação | K18: Product Owner | L18: Meeting | M18: Gestores Cannoli | N18: Após cada reunião | P18: Retorno sobre aderência às necessidades do negócio. | S18: Após cada reunião | X18: Ajustes feitos no sprint seguinte.
A19: Equipe de Comunicação do InovaTech | B19: Médio – responsáveis pela apresentação e divulgação do projeto. | C19: Baixo – têm papel informativo, reforçando a imagem do projeto e sua importância. | D19: Produzir materiais visuais, relatórios e apresentações de resultados. | G19: STK-005 | H19: Testes de Integração e Dados | I19: Avaliar funcionamento da integração com o sistema da Cannoli e confiabilidade dos dados. | J19: Sessão Técnica | K19: Equipe de Dados e Devs | L19: Meeting | M19: Time Técnico | N19: A cada 15 dias | P19: Relato de erros e inconsistências encontradas. | S19: Após cada reunião | X19: Correção e revalidação antes da entrega.
G20: STK-006 | H20: Reunião com Orientadores | I20: Atualização do progresso acadêmico e das etapas de desenvolvimento. | J20: Reunião Acadêmica | K20: Gerente de Projeto | L20: Meeting | M20: Professores e Avaliadores | N20: Semanalmente | P20: Feedback sobre metodologia e entregas. | S20: Após cada sessão | X20: Sugestões de melhoria registradas no relatório.
G21: STK-007 | H21: Apresentação Parcial | I21: Demonstração do dashboard funcional e indicadores principais. | J21: Reunião de Apresentação | K21: Gerente de Projeto / UX | L21: Meeting | M21: Professores e Representantes da Cannoli | N21: A cada 2 semanas | P21: Feedback visual e funcional sobre o sistema. | S21: Após cada reunião | X21: Ajustes visuais e de performance.
G22: STK-008 | H22: Reunião de Encerramento | I22: Apresentação final do InovaTech, resultados alcançados e lições aprendidas. | J22: Reunião Final | K22: Gerente de Projeto | L22: Meeting | M22: Equipe InovaTech, Professores e Cannoli | N22: Mensalmente | P22: Avaliação do impacto e resultados. | S22: Após cada reunião | X22: Registro em ata e documentação final.
H24: Gerente do projeto: Bruna Lira | J24: Elaborado por: InovaTech | N24: Aprovado por: Rafaela Bastos (Gerente)

Sheet Planejamento de RH
D6: Gestão de RH
D9: Nome | E9: Função | F9: Origem | G9: Dedicação (horas)
D10: Adeilson Nunes | E10: Assistente de Testes | F10: TI – Apoio Operacional | G10: 4
D11: Bruna Lira | E11: Gerente de Projeto e Analista de Negócios | F11: Gerência (Interno) | Desenvolvimento | G11: 8
D12: Daniela Pauzer | E12: Assistente de Pesquisa | F12: Comunicação (Interno/Externo) | G12: 4
D13: Enzo Sangiacomo | E13: Apoio Técnico | F13: TI – Apoio Técnico | G13: 5
D14: Rafaela Coelho | E14: Desenvolvedora Full Stack e Líder Técnica | F14: TI – Desenvolvimento | Gerencia | G14: 8
D19: Planejamento de RH

Sheet Organograma da Equipe

Sheet Mapa Competência - Equipe
B8: Perfil de Qualificação | G8: MAPA DE COMPETÊNCIAS
B9: 0 | C9: Nenhum conhecimento | J9: Saúde e Bem Estar
B10: 2 | C10: Participou de treinamento | G10: Revisado em Nov/2025
B11: 5 | C11: Domínio básico | G11: Sistema: InovaTech - Dashboard Inteligente
B12: 8 | C12: Experiência prática | G12: Responsável: Bruna
B13: 10 | C13: Especialista | G13: Habilitação
F14: Pessoa | G14: Definição e Priorização de Backlog | H14: Planejar Atividades | I14: Projetar Interface do Usuário | J14: Integrar Sistema e Banco de Dados | K14: Utilizar Figma | L14: Utilizar VSCode | M14: Planejamento Estratégico | N14: Gerenciar Projetos | O14: Plano de Gerenciamento de RH | P14: Controle de Qualidade | Q14: Elaborar a W.B.S | R14: Mitigar Riscos | S14: Documentação Técnica | T14: Criar wireframes | U14: Procedimentos Administrativos | V14: Faturamento da Startup
D15: Adeilson Nunes | G15: 5 | H15: 8 | I15: 2 | J15: 2 | K15: 2 | L15: 5 | M15: 5 | N15: 5 | O15: 2 | P15: 8 | Q15: 10 | R15: 8 | S15: 5 | T15: 5 | U15: 8 | V15: 8
D16: Bruna Lira | G16: 10 | H16: 8 | I16: 10 | J16: 5 | K16: 10 | L16: 10 | M16: 10 | N16: 10 | O16: 10 | P16: 10 | Q16: 8 | R16: 8 | S16: 8 | T16: 10 | U16: 10 | V16: 10
D17: Daniela Pauzer | G17: 5 | H17: 8 | I17: 2 | J17: 2 | K17: 2 | L17: 5 | M17: 5 | N17: 5 | O17: 2 | P17: 8 | Q17: 10 | R17: 8 | S17: 5 | T17: 5 | U17: 8 | V17: 8
D18: Enzo Sangiacomo | G18: 5 | H18: 8 | I18: 5 | J18: 2 | K18: 5 | L18: 5 | M18: 8 | N18: 5 | O18: 2 | P18: 8 | Q18: 10 | R18: 8 | S18: 8 | T18: 5 | U18: 10 | V18: 5
D19: Rafaela Coelho | G19: 10 | H19: 8 | I19: 10 | J19: 10 | K19: 8 | L19: 10 | M19: 10 | N19: 10 | O19: 5 | P19: 10 | Q19: 8 | R19: 10 | S19: 8 | T19: 8 | U19: 10 | V19: 10

Sheet Mapa de Responsabilidade
B2: 6. Matriz de Responsabilidade
D4: Equipe do Projeto
B5: Ref | C5: Etapas – Atividades | D5: AN | E5: BL | F5: ES | G5: DP | H5: RC
B6: 1.1 | C6: Levantamento das necessidades da empresa parceira (Cannoli Restaurante) | D6: P | E6: A | F6: P | G6: P | H6: P
B7: 1.2 | C7: Definição dos objetivos do dashboard inteligente | D7: C | E7: R/A | F7: P | G7: P | H7: R
B8: 1.3 | C8: Criação do escopo técnico e funcional do projeto | D8: P | E8: R | F8: P | G8: P | H8: R/A
B9: 1.4 | C9: Reunião de alinhamento inicial com a empresa parceira | D9: P | E9: P | F9: P | G9: P | H9: A
B10: 1.5 | C10: Pesquisa sobre tecnologias aplicáveis e ferramentas de integração | D10: R | E10: R/A | F10: R | G10: R | H10: R
B11: 1.6 | C11: Identificação de riscos e restrições do projeto | D11: I | E11: R | F11: I | G11: I | H11: A
B12: 1.7 | C12: Definição dos papéis e responsabilidades da equipe | D12: I | E12: R | F12: I | G12: I | H12: A
B13: 1.8 | C13: Elaboração do plano de comunicação interna e externa | D13: I | E13: R | F13: P | G13: P | H13: A
B14: 1.9 | C14: Criação do cronograma base e estimativa de tempo de execução | D14: P | E14: R | F14: P | G14: P | H14: P/A
B15: 1.10 | C15: Validação inicial com o cliente (Cannoli) | D15: P | E15: P/A | F15: P | G15: P | H15: P
B16: 1.11 | C16: Pesquisas sobre Inteligência Artificial aplicada a sistemas de recomendação | D16: R | E16: I | F16: P | G16: R/A | H16: I
... B19: 1.14 | C19: Criação da Estrutura Analítica do Projeto (WBS) | D19: P | E19: R/A | F19: P | G19: P | H19: P
B20: 1.15 | C20: Elaboração da Planilha de Plano de Custo | D20: I | E20: R | F20: I | G20: I | H20: A | J20: EQUIPE DO PROJETO
B21: 1.16 | C21: Elaboração da Planilha de Plano de RH | D21: I | E21: R | F21: I | G21: I | H21: A | J21: Adeilson Nunes | K21: Assistente de Testes
B22: 1.17 | C22: Elaboração da Planilha de Plano de Comunicação | D22: I | E22: R | F22: I | G22: I | H22: A | J22: Bruna Lira | K22: Gerente de Projeto e Analista de Negócios
B23: 1.18 | C23: Elaboração da Planilha de Plano de Riscos | D23: I | E23: R | F23: I | G23: I | H23: A | J23: Enzo Sangiacomo | K23: Apoio Técnico
B24: 1.19 | C24: Criação da identidade visual e Logo do InovaTech | D24: C | E24: R | F24: C | G24: C | H24: C/A | J24: Daniela Pauzer | K24: Assistente de Pesquisa
B25: 1.20 | C25: Desenvolvimento de Personas do sistema InovaTech | D25: P | E25: R | F25: P | G25: P | H25: A | J25: Rafaela Coelho | K25: Desenvolvedora Full Stack e Líder Técnica
B26: 1.21 | C26: Modelagem de Negócios utilizando o Canvas | D26: P | E26: R/A | F26: P | G26: P | H26: P
B27: 1.22 | C27: Elaboração do Documento de Segurança seguindo o método GUT | D27: I | E27: R | F27: I | G27: I | H27: A
B28: 2.1 | C28: Criação do wireframe no Figma | D28: I | E28: R | F28: I | G28: I | H28: A
B29: 2.2 | C29: Desenvolvimento do design de interface (UI) | D29: I | E29: R | F29: I | G29: I | H29: A | J29: Legenda - - Gráfico RACI (Responsabilidade, Aprovação, Consultado e Informado)
B30: 2.3 | C30: Modelagem da experiência do usuário (UX) | D30: I | E30: R | F30: I | G30: I | H30: C/A
B31: 2.4 | C31: Aplicação da identidade visual do InovaTech | D31: I | E31: R | F31: I | G31: I | H31: A | J31: R - Responsável pela Execução
B32: 2.5 | C32: Testes de navegabilidade e ajustes visuais | D32: I | E32: R/A | F32: I | G32: I | H32: P | J32: A - Aprovação
B33: 2.6 | C33: Aprovação do protótipo pelo cliente | D33: I | E33: R | F33: I | G33: I | H33: A | J33: C - Consultado
B34: 3.1 | C34: Configuração do ambiente de desenvolvimento | D34: I | E34: P/A | F34: I | G34: I | H34: R | J34: I - Informado
B35: 3.2 | C35: Criação do banco de dados SQLite | D35: I | E35: A | F35: I | G35: I | H35: R | J35: P - Participante
B36: 3.3 | C36: Desenvolvimento da API utilizando Python (Flask) | D36: I | E36: P/A | F36: I | G36: I | H36: R
B37: 3.4 | C37: Implementação do front-end em React | D37: I | E37: P/A | F37: I | G37: I | H37: R/A
B38: 3.5 | C38: Criação dos componentes reutilizáveis de interface | D38: I | E38: A | F38: I | G38: I | H38: R/A
B39: 3.6 | C39: Integração entre front-end e back-end | D39: I | E39: A | F39: I | G39: I | H39: R/A
B40: 3.7 | C40: Implementação de gráficos e relatórios dinâmicos | D40: I | E40: A | F40: I | G40: I | H40: R/A
B41: 3.8 | C41: Autenticação e controle de acesso de usuários | D41: I | E41: P/A | F41: I | G41: I | H41: R/A
B42: 3.9 | C42: Configuração das rotas e endpoints da API | D42: I | E42: A | F42: I | G42: I | H42: R
B43: 3.10 | C43: Tratamento de erros e implementação de logs | D43: I | E43: A | F43: I | G43: I | H43: R
B44: 3.11 | C44: Testes de integração entre os módulos | D44: I | E44: A | F44: I | G44: I | H44: R
B45: 3.12 | C45: Documentação do código e versionamento no GitHub | D45: I | E45: A | F45: I | G45: I | H45: R
B46: 3.13 | C46: Entrega da aplicação de Inteligência Artificial | D46: C | E46: R/A | F46: P | G46: C | H46: R
B47: 3.14 | C47: Entrega da aplicação de Machine Learning | D47: I | E47: R/A | F47: I | G47: I | H47: R
... B63: 5.10 | C63: Planejamento de evolução futura do sistema | D63: I | E63: R/A | F63: I | G63: I | H63: R

Sheet Gráfico de Gantt
E3: Saúde e bem-estar na palma da sua mão
A5: Insira o nome do Líder do projeto na célula B3. Insira a data de Início do projeto na célula E3. Início do projeto: o rótulo está na célula C3. | D5: Líder do projeto: Gerente de Projeto | E5: Início do projeto: | G5: 45160
A6: A semana de exibição na célula E4 representa a semana inicial a ser exibida no cronograma do projeto na célula I4. A data de início do projeto é considerada Semana 1. Para alterar a semana de exibição, basta inserir um novo número da semana na célula E4. A data inicial para cada semana, começando com a semana de exibição na célula E4, começa na célula I4 e é calculada automaticamente. Há 8 semanas representadas nesse modo de exibição que vão da célula I4 a célula BF4. Você não deve modificar essas células. Semana de exibição: o rótulo está na célula C4. | E6: Semana de exibição: | G6: 1 | K6: =K7 -> 45159 | R6: =R7 -> 45166 | Y6: =Y7 -> 45173 | AF6: =AF7 -> 45180 | AM6: =AM7 -> 45187 | AT6: =AT7 -> 45194 | BA6: =BA7 -> 45201 | BH6: =BH7 -> 45208
A7: As células I5 a BL5 contêm o número de dias da semana representado no bloco de células acima de cada célula de data e são calculadas automaticamente. Você não deve modificar essas células. A data de hoje é contornada em vermelho (hex #AD3815) a partir da data de hoje na linha 5, passando pela coluna de data inteira até o final do cronograma do projeto. | K7: =Início_do_projeto-WEEKDAY(Início_do_projeto,1)+2+7*(Semana_de_exibição-1) -> 45159 | L7: =K7+1 -> 45160 | M7: =L7+1 -> 45161 | N7: =M7+1 -> 45162 | O7: =N7+1 -> 45163 | P7: =O7+1 -> 45164 | Q7: =P7+1 -> 45165 | R7: =Q7+1 -> 45166 | S7: =R7+1 -> 45167 | ... BN7: =BM7+1 -> 45214
A8: Esta linha inclui cabeçalhos do cronograma do projeto que estão abaixo deles. Navegue de B6 a BL6 para ouvir o conteúdo. A primeira letra de cada dia da semana da data acima daquele cabeçalho começa na célula I6 e continua até a célula BL6. Todo o gráfico de linha do tempo de projeto é gerado automaticamente com base nas datas de início e término inseridas, usando os formatos condicionais. Não modifique o conteúdo nas células dentro das colunas após a coluna I, começando na célula I7. | D8: TAREFA | E8: ATRIBUÍDO PARA | F8: PROGRESSO | G8: INÍCIO | H8: TÉRMINO | J8: DIAS | K8: =LEFT(TEXT(K7,"ddd"),1) -> s | L8: =LEFT(TEXT(L7,"ddd"),1) -> t | M8: =LEFT(TEXT(M7,"ddd"),1) -> q | N8: =LEFT(TEXT(N7,"ddd"),1) -> q | O8: =LEFT(TEXT(O7,"ddd"),1) -> s | P8: =LEFT(TEXT(P7,"ddd"),1) -> s | Q8: =LEFT(TEXT(Q7,"ddd"),1) -> d | R8: =LEFT(TEXT(R7,"ddd"),1) -> s | ... BN8: =LEFT(TEXT(BN7,"ddd"),1) -> d
A9: Não exclua esta linha. Esta linha ficará oculta para preservar uma fórmula usada para realçar o dia atual no cronograma do projeto. | J9: =IF(OR(ISBLANK(início_da_tarefa),ISBLANK(término_da_tarefa)),"",término_da_tarefa-início_da_tarefa+1) -> 4
A10: A célula B8 contém o título do exemplo da Fase 1. Insira um novo Título na célula B8. Na célula C8, insira o nome a atribuir à fase, caso ela se aplique ao seu projeto. Na célula D8, insira o Progresso para a fase inteira, caso ela se aplique ao seu projeto. Nas células E8 e F8, insira as datas de início e término para a fase inteira, caso ela se aplique ao seu projeto. O gráfico de Gantt preenche automaticamente as datas apropriadas e sombreia de acordo com o andamento inserido. Para excluir a fase e trabalhar apenas nas tarefas, basta excluir essa linha. | D10: Iniciação | J10: =IF(OR(ISBLANK(início_da_tarefa),ISBLANK(término_da_tarefa)),"",término_da_tarefa-início_da_tarefa+1) -> 3
A11: A célula B9 contém a tarefa de exemplo "Tarefa 1". Insira um novo nome da tarefa na célula B9. Insira uma pessoa para atribuir a tarefa na célula C9. Insira o andamento da tarefa na célula D9. Uma barra de progresso é exibida na célula e fica sombreada de acordo com o número na célula. Por exemplo, 50% de progresso sombreia metade da célula. Insira a data de início da tarefa na célula E9. Insira a data de término da tarefa na célula F9. Uma barra de status sombreada das datas inseridas aparece em blocos começando na célula I9 até BL9. | D11: Definir os objetivos do aplicativo e sua proposta de valor | G11: =Início_do_projeto -> 45160 | H11: =G11+3 -> 45163 | J11: =IF(OR(ISBLANK(início_da_tarefa),ISBLANK(término_da_tarefa)),"",término_da_tarefa-início_da_tarefa+1) -> 5
A12: As linhas 10 a 13 repetem o padrão da linha 9. Repita as instruções da célula A9 para todas as linhas de tarefas nesta planilha. Substitua os dados de exemplo. Um exemplo de outra fase começa na célula A14. Continue inserindo tarefas nas células A10 a A13 ou vá para a célula A14 para saber mais. | D12: Tarefa 2 | J12: =IF(OR(ISBLANK(início_da_tarefa),ISBLANK(término_da_tarefa)),"",término_da_tarefa-início_da_tarefa+1) -> 6
D13: Tarefa 3 | J13: =IF(OR(ISBLANK(início_da_tarefa),ISBLANK(término_da_tarefa)),"",término_da_tarefa-início_da_tarefa+1) -> 3
D14: Tarefa 4 | J14: =IF(OR(ISBLANK(início_da_tarefa),ISBLANK(término_da_tarefa)),"",término_da_tarefa-início_da_tarefa+1)
D15: Tarefa 5 | J15: =IF(OR(ISBLANK(início_da_tarefa),ISBLANK(término_da_tarefa)),"",término_da_tarefa-início_da_tarefa+1) -> 5
A16: A célula à direita contém o título do exemplo da Fase 2. Você pode criar uma nova fase a qualquer momento na coluna B. Este cronograma de projeto não exige fases. Para remover a fase, basta excluir a linha. Para criar um novo bloco de fases nesta linha, digite um novo Título na célula à direita. Para continuar a adicionar tarefas à fase acima, insira uma nova linha acima desta e preencha os dados da tarefa como na instrução da célula A9. Atualize os detalhes da Fase na célula à direita, com base nas instruções da célula A8. Continue navegando para baixo nas células da coluna A para saber mais. Se você ainda não adicionou as novas linhas nesta planilha, encontrará 2 exemplos adicionais de blocos de fase que foram criados nas células B20 e B26. Caso contrário, navegue pelas células da coluna A para localizar os blocos adicionais. Repita as instruções das células A8 e A9 sempre que precisar. | D16: Título Fase 2 | J16: =IF(OR(ISBLANK(início_da_tarefa),ISBLANK(término_da_tarefa)),"",término_da_tarefa-início_da_tarefa+1) -> 6
D17: Tarefa 1 | J17: =IF(OR(ISBLANK(início_da_tarefa),ISBLANK(término_da_tarefa)),"",término_da_tarefa-início_da_tarefa+1) -> 4
D18: Tarefa 2 | J18: =IF(OR(ISBLANK(início_da_tarefa),ISBLANK(término_da_tarefa)),"",término_da_tarefa-início_da_tarefa+1) -> 3
D19: Tarefa 3 | J19: =IF(OR(ISBLANK(início_da_tarefa),ISBLANK(término_da_tarefa)),"",término_da_tarefa-início_da_tarefa+1) -> 4
D20: Tarefa 4 | J20: =IF(OR(ISBLANK(início_da_tarefa),ISBLANK(término_da_tarefa)),"",término_da_tarefa-início_da_tarefa+1)
D21: Tarefa 5 | J21: =IF(OR(ISBLANK(início_da_tarefa),ISBLANK(término_da_tarefa)),"",término_da_tarefa-início_da_tarefa+1) -> 6
A22: Bloco de título de fase de exemplo | D22: Título Fase 3 | J22: =IF(OR(ISBLANK(início_da_tarefa),ISBLANK(término_da_tarefa)),"",término_da_tarefa-início_da_tarefa+1) -> 5
D23: Tarefa 1 | J23: =IF(OR(ISBLANK(início_da_tarefa),ISBLANK(término_da_tarefa)),"",término_da_tarefa-início_da_tarefa+1) -> 6
D24: Tarefa 2 | J24: =IF(OR(ISBLANK(início_da_tarefa),ISBLANK(término_da_tarefa)),"",término_da_tarefa-início_da_tarefa+1) -> 5
D25: Tarefa 3 | J25: =IF(OR(ISBLANK(início_da_tarefa),ISBLANK(término_da_tarefa)),"",término_da_tarefa-início_da_tarefa+1) -> 5
D26: Tarefa 4 | J26: =IF(OR(ISBLANK(início_da_tarefa),ISBLANK(término_da_tarefa)),"",término_da_tarefa-início_da_tarefa+1)
D27: Tarefa 5 | J27: =IF(OR(ISBLANK(início_da_tarefa),ISBLANK(término_da_tarefa)),"",término_da_tarefa-início_da_tarefa+1) -> #VALUE!
A28: Bloco de título de fase de exemplo | D28: Título Fase 4 | J28: =IF(OR(ISBLANK(início_da_tarefa),ISBLANK(término_da_tarefa)),"",término_da_tarefa-início_da_tarefa+1) -> #VALUE!
D29: Tarefa 1 | G29: data | H29: data | J29: =IF(OR(ISBLANK(início_da_tarefa),ISBLANK(término_da_tarefa)),"",término_da_tarefa-início_da_tarefa+1) -> #VALUE!
D30: Tarefa 2 | G30: data | H30: data | J30: =IF(OR(ISBLANK(início_da_tarefa),ISBLANK(término_da_tarefa)),"",término_da_tarefa-início_da_tarefa+1) -> #VALUE!
D31: Tarefa 3 | G31: data | H31: data | J31: =IF(OR(ISBLANK(início_da_tarefa),ISBLANK(término_da_tarefa)),"",término_da_tarefa-início_da_tarefa+1) -> #VALUE!
D32: Tarefa 4 | G32: data | H32: data | J32: =IF(OR(ISBLANK(início_da_tarefa),ISBLANK(término_da_tarefa)),"",término_da_tarefa-início_da_tarefa+1)
D33: Tarefa 5 | G33: data | H33: data | J33: =IF(OR(ISBLANK(início_da_tarefa),ISBLANK(término_da_tarefa)),"",término_da_tarefa-início_da_tarefa+1)
A34: Esta é uma linha vazia | J34: =IF(OR(ISBLANK(início_da_tarefa),ISBLANK(término_da_tarefa)),"",término_da_tarefa-início_da_tarefa+1)
A35: Esta linha marca o final do Cronograma do projeto. NÃO insira nada nessa linha. Insira novas linhas ACIMA desta linha para continuar a construção do cronograma de projeto. | D35: Insira novas linhas ACIMA desta | J35: =IF(OR(ISBLANK(início_da_tarefa),ISBLANK(término_da_tarefa)),"",término_da_tarefa-início_da_tarefa+1)

Sheet PV_dependência
A3: Soma de Custos
A4: Dependência | B4: Responsável | C4: Etapas – Atividades - | D4: Ref | E4: Total
A5: 1.1 | B5: GERENTE DE PROJETO | C5: Definir os objetivos do aplicativo e sua proposta de valor | D5: 1.1 | E5: 1000
C6: Formar uma equipe de desenvolvimento e design | D6: 1.3 | E6: 1000
C7: Identificar as principais funcionalidades e recursos a serem incluídos | D7: 1.2 | E7: 2000
A8: 1.3 | B8: DESIGN | C8: Realizar o design da interface do usuário (UI) | D8: 3.1 | E8: 2000
B9: GERENTE DE PROJETO | C9: Definir os requisitos detalhados do aplicativo (escopo) | D9: 2.2 | E9: 700
B10: (vazio) | C10: Planejamento | D10: 2
A11: 10.1.1 | B11: DESEMPENHO | C11: Realizar análises regulares sobre o desempenho do aplicativo | D11: 10.1.1 | E11: 4000
A12: 10.1.2 | B12: COMERCIAL | C12: Explorar parcerias com empresas relacionadas à saúde e bem-estar | D12: 10.1.2 | E12: 1000
A13: 10.1.3 | B13: COMERCIAL | C13: Avaliar a possibilidade de oferecer versões premium ou modelos de assinatura | D13: 10.1.3 | E13: 1000
A14: 2.1 | B14: GERENTE DE PROJETO | C14: Realizar uma análise de mercado para entender concorrentes e demandas | D14: 2.1 | E14: 2000
A15: 2.2 | B15: GERENTE DE PROJETO | C15: Criar um cronograma detalhado com marcos e prazos | D15: 2.3 | E15: 400
C16: Dicas de saúde e bem-estar | D16: 2.2.1 | E16: 500
C17: Integração com sistemas de monitoramento de saúde | D17: 2.2.4 | E17: 200
C18: Mapas com locais de academias e parques | D18: 2.2.3 | E18: 800
C19: Planos de exercícios físicos personalizados | D19: 2.2.2 | E19: 1000
A20: 2.3 | B20: (vazio) | C20: Design e Prototipagem | D20: 3
A21: 3.1 | B21: DESIGN | C21: Navegação simples entre as funcionalidades | D21: 3.1.1 | E21: 500
A22: 3.1.1 | B22: DESIGN | C22: Criar protótipos interativos para validar o fluxo de usuário | D22: 3.1.2 | E22: 500
A23: 3.1.2 | B23: DESIGN | C23: Experiência do usuário (UX) | D23: 3.2 | E23: 1000
A24: 3.2 | B24: DESIGN | C24: Interface limpa e intuitiva | D24: 3.2.1 | E24: 500
A25: 3.2.1 | B25: (vazio) | C25: Desenvolvimento | D25: 4
A26: 3.2.2 | B26: DESIGN | C26: Teste de UI / UX | D26: 3.2.2 | E26: 700
A27: 4.1 | B27: DESENVOLVIMENTO | C27: Desenvolver a estrutura do aplicativo | D27: 4.1 | E27: 500
A28: 4.1.2 | B28: DESENVOLVIMENTO | C28: Front-end: Interface do usuário e interações | D28: 4.1.2 | E28: 5000
A29: 4.2 | B29: DESENVOLVIMENTO | C29: Implementar as funcionalidades principais | D29: 4.2 | E29: 700
A30: 4.2.1 | B30: DESENVOLVIMENTO | C30: Módulo de dicas de saúde | D30: 4.2.1 | E30: 500
A31: 4.2.2 | B31: DESENVOLVIMENTO | C31: Gerador de planos de exercícios | D31: 4.2.2 | E31: 300
A32: 4.2.3 | B32: DESENVOLVIMENTO | C32: Integração com APIs de mapas para localização de academias e parques | D32: 4.2.3 | E32: 1000
A33: 5.1 | B33: SEGURANÇA | C33: Integrar o aplicativo com sistemas de monitoramento de saúde, como dispositivos wearable ou aplicativos de rastreamento | D33: 5.1 | E33: 3000
A34: 5.2 | B34: SEGURANÇA | C34: Garantir a segurança e privacidade dos dados do usuário | D34: 5.2 | E34: 1000
A35: 5.3 | B35: SEGURANÇA | C35: Testar a integração para assegurar que os dados são sincronizados corretamente | D35: 5.3 | E35: 1000
A36: 6.1 | B36: QUALIDADE | C36: Realizar testes de qualidade e desempenho em diversas plataformas (iOS, Android) | D36: 6.1 | E36: 30000
A37: 6.1.2 | B37: UX | C37: Testar a usabilidade do aplicativo com usuários reais | D37: 6.1.2 | E37: 700
... A47: 9.1.3 | B47: EQUIPE TÉCNICA | C47: Realizar campanhas de mídia social e anúncios online | D47: 9.1.3 | E47: 10000
A48: (vazio) | B48: (vazio) | C48: Avaliação e Aperfeiçoamento | D48: 10
C49: Iniciação | D49: 1
C50: Integração com sistemas de monitoramento de saúde | D50: 5
C51: Lançamento | D51: 7
C52: Marketing e Divulgação | D52: 9
C53: Pós-lançamento | D53: 8
C54: Testes | D54: 6
A55: Total Geral | E55: 150000

Sheet Cronograma_de_Custos (2)
B2: 5.2. CRONOGRAMA DE CUSTOS
B5: Ref | C5: Etapas – Atividades - Marcos
D6: 1 | E6: 2 | F6: 3 | G6: 4 | H6: 5 | I6: 6 | J6: 7 | K6: 8 | L6: 9 | M6: 10 | N6: 11 | O6: 12 | P6: 13 | Q6: 14 | R6: 15 | S6: 16 | T6: 17 | U6: 18 | V6: 19 | W6: 20 | X6: 21 | Y6: 22 | Z6: 23 | AA6: 24
D7: Agosto | H7: Setembro | L7: Outubro | P7: Novembro | T7: Dezembro | X7: Janeiro
B8: 1.1 | C8: Plano do Projeto | D8: 30000
B9: 1.2 | C9: Controle | H9: 5000 | L9: 5000 | P9: 5000 | T9: 5000
B10: 1.3 | C10: Fechamento | X10: 10000
B11: 2 | C11: Adequar o Espaço Físico | L11: 20000 | P11: 40000 | T11: 10000 | X11: 10000
B12: 3.1 | C12: Equipamentos de Ginástica | H12: 10000 | L12: 25000 | P12: 25000 | T12: 25000 | X12: 5000
B13: 3.2 | C13: Equipamentos de Apoio e Administração | L13: 15000 | P13: 15000 | T13: 20000 | X13: 10000
B14: 4 | C14: Contratar Mão de Obra | X14: 7000
B15: 5.1 | C15: Contratar empresa para informatização da academia | T15: 4000 | X15: 4000
B16: 5.2 | C16: Adquirir Sistemas de Segurança | T16: 2500 | X16: 2500
B17: 5.3 | C17: Fechar Convênio com Estacionamento próximo ao local | X17: 0
B18: 5.4 | C18: Contratação de Designer de Interiores | H18: =20000*35% -> 7000 | L18: =13000/4 -> 3250 | P18: =13000/4 -> 3250 | T18: =13000/4 -> 3250 | X18: =13000/4 -> 3250
